{
  "actor": {
    "name": "姫野ことめ",
    "birthday": "2000/7/16",
    "age": "25",
    "matched": false,
    "actor_id": "zukrU4xw",
    "binghuo_person_id": "1835",
    "binghuo_height": "158",
    "binghuo_bust": "82",
    "binghuo_cup": "D",
    "binghuo_waist": "54",
    "binghuo_hip": "85",
    "baomu_birthday": "2000-07-15",
    "baomu_height": "158",
    "baomu_bust": "82",
    "baomu_cup": "D",
    "baomu_waist": "54",
    "baomu_hip": "85",
    "baomu_enrichment_status": "已补全",
    "web_url": "https://avfan.com/casts/zukrU4xw",
    "ladder_tier": "",
    "update_status": "inactive",
    "local_video_count": 0,
    "appearance_code_count": 34,
    "code_prefix_library_count": 6,
    "local_prefix_distribution": [],
    "local_year_distribution": [],
    "web_enrichment_status": "天限阁: 已补全 | 辛聚谷: 已补全 | 并火: 已补全 | 保木: 已补全",
    "web_total_pages": 3,
    "web_total_videos": 98,
    "eligible_video_count": 38,
    "eligible_enriched_video_count": 38,
    "web_update_frequency": {
      "video_count": 38,
      "month_count": 67,
      "videos_per_month": 0.5671641791044776
    },
    "web_last_enriched_at": "2026-06-30 02:34:02",
    "web_earliest_release_date": "2020-02-01",
    "web_latest_release_date": "2025-08-08",
    "web_prefix_distribution": [
      {
        "prefix": "INST",
        "video_count": 2
      },
      {
        "prefix": "KAMEF",
        "video_count": 2
      },
      {
        "prefix": "MDBK",
        "video_count": 2
      },
      {
        "prefix": "TCNB",
        "video_count": 2
      },
      {
        "prefix": "ADN",
        "video_count": 1
      },
      {
        "prefix": "APKH",
        "video_count": 1
      },
      {
        "prefix": "APNS",
        "video_count": 1
      },
      {
        "prefix": "ATID",
        "video_count": 1
      },
      {
        "prefix": "BBAN",
        "video_count": 1
      },
      {
        "prefix": "BIG",
        "video_count": 1
      },
      {
        "prefix": "CLO",
        "video_count": 1
      },
      {
        "prefix": "DAC",
        "video_count": 1
      },
      {
        "prefix": "FRIN",
        "video_count": 1
      },
      {
        "prefix": "GVH",
        "video_count": 1
      },
      {
        "prefix": "HUNTA",
        "video_count": 1
      },
      {
        "prefix": "KWBD",
        "video_count": 1
      },
      {
        "prefix": "LAS",
        "video_count": 1
      },
      {
        "prefix": "MAXVR",
        "video_count": 1
      },
      {
        "prefix": "MFC",
        "video_count": 1
      },
      {
        "prefix": "MKON",
        "video_count": 1
      },
      {
        "prefix": "MXX",
        "video_count": 1
      },
      {
        "prefix": "NAMA",
        "video_count": 1
      },
      {
        "prefix": "OPCYN",
        "video_count": 1
      },
      {
        "prefix": "ORE",
        "video_count": 1
      },
      {
        "prefix": "OREC",
        "video_count": 1
      },
      {
        "prefix": "OVG",
        "video_count": 1
      },
      {
        "prefix": "SHIND",
        "video_count": 1
      },
      {
        "prefix": "SHINKI",
        "video_count": 1
      },
      {
        "prefix": "SIRO",
        "video_count": 1
      },
      {
        "prefix": "STVF",
        "video_count": 1
      },
      {
        "prefix": "SUPA",
        "video_count": 1
      },
      {
        "prefix": "SVDVD",
        "video_count": 1
      },
      {
        "prefix": "VOSM",
        "video_count": 1
      },
      {
        "prefix": "ZKWD",
        "video_count": 1
      }
    ],
    "web_year_distribution": [
      {
        "year": "2025",
        "video_count": 1
      },
      {
        "year": "2024",
        "video_count": 2
      },
      {
        "year": "2023",
        "video_count": 5
      },
      {
        "year": "2022",
        "video_count": 1
      },
      {
        "year": "2021",
        "video_count": 8
      },
      {
        "year": "2020",
        "video_count": 21
      }
    ],
    "web_video_category_distribution": [
      {
        "name": "单体作品",
        "video_count": 6
      },
      {
        "name": "共演作品",
        "video_count": 6
      },
      {
        "name": "合集作品",
        "video_count": 2
      },
      {
        "name": "暂无分类信息",
        "video_count": 24
      }
    ],
    "local_videos": [],
    "web_movies": [
      {
        "actor_name": "姫野ことめ",
        "code": "TCNB-062",
        "title": "ともか",
        "author": "",
        "release_date": "2025-08-08",
        "avfan_url": "https://avfan.com/zh-CN/movies/9KCwHAg9",
        "page_number": 1,
        "javtxt_enrichment_status": "无搜索结果",
        "javtxt_movie_id": "",
        "javtxt_url": "",
        "javtxt_tags": "",
        "javtxt_release_date": "",
        "author_raw": "",
        "video_category": "",
        "supplement_enrichment_status": "未补全",
        "ladder_tags": [],
        "ladder_tag_text": ""
      },
      {
        "actor_name": "姫野ことめ",
        "code": "TCNB-022",
        "title": "ともか",
        "author": "",
        "release_date": "2024-11-01",
        "avfan_url": "https://avfan.com/zh-CN/movies/enA6b3Fj",
        "page_number": 1,
        "javtxt_enrichment_status": "无搜索结果",
        "javtxt_movie_id": "",
        "javtxt_url": "",
        "javtxt_tags": "",
        "javtxt_release_date": "",
        "author_raw": "",
        "video_category": "",
        "supplement_enrichment_status": "未补全",
        "ladder_tags": [],
        "ladder_tag_text": ""
      },
      {
        "actor_name": "姫野ことめ",
        "code": "CLO-325",
        "title": "人気の無くなった学校で、あの娘と…。",
        "author": "姫野ことめ",
        "release_date": "2024-05-10",
        "avfan_url": "https://avfan.com/zh-CN/movies/r41ymLv1",
        "page_number": 1,
        "javtxt_enrichment_status": "已补全",
        "javtxt_movie_id": "471633",
        "javtxt_url": "https://javtxt.top/v/471633",
        "javtxt_tags": "高清 单体作品 口交 指交 水手服 女子校生 美少女",
        "javtxt_release_date": "2024-05-10",
        "author_raw": "姫野ことめ",
        "video_category": "单体作品",
        "supplement_enrichment_status": "未补全",
        "ladder_tags": [],
        "ladder_tag_text": ""
      },
      {
        "actor_name": "姫野ことめ",
        "code": "KWBD-361",
        "title": "可爱女孩激情高潮！同步绝顶的最后冲刺正常位内射105连发",
        "author": "",
        "release_date": "2023-12-29",
        "avfan_url": "https://avfan.com/zh-CN/movies/fVtnPiUO",
        "page_number": 1,
        "javtxt_enrichment_status": "无搜索结果",
        "javtxt_movie_id": "",
        "javtxt_url": "",
        "javtxt_tags": "",
        "javtxt_release_date": "2023-12-29",
        "author_raw": "",
        "video_category": "合集作品",
        "supplement_enrichment_status": "未补全",
        "ladder_tags": [],
        "ladder_tag_text": ""
      },
      {
        "actor_name": "姫野ことめ",
        "code": "VOSM-054",
        "title": "VRHQ剧超高画质500分钟！深情对视＆亲密互动中正常体位下可爱脸蛋尽情观赏！无限快感！精选55位女优",
        "author": "",
        "release_date": "2023-12-01",
        "avfan_url": "https://avfan.com/zh-CN/movies/L4clcOzh",
        "page_number": 1,
        "javtxt_enrichment_status": "无搜索结果",
        "javtxt_movie_id": "",
        "javtxt_url": "",
        "javtxt_tags": "",
        "javtxt_release_date": "",
        "author_raw": "",
        "video_category": "",
        "supplement_enrichment_status": "未补全",
        "ladder_tags": [],
        "ladder_tag_text": ""
      },
      {
        "actor_name": "姫野ことめ",
        "code": "MDBK-312",
        "title": "大量内射 -",
        "author": "",
        "release_date": "2023-11-28",
        "avfan_url": "https://avfan.com/zh-CN/movies/AI7YzU0g",
        "page_number": 1,
        "javtxt_enrichment_status": "无搜索结果",
        "javtxt_movie_id": "",
        "javtxt_url": "",
        "javtxt_tags": "",
        "javtxt_release_date": "",
        "author_raw": "",
        "video_category": "共演作品",
        "supplement_enrichment_status": "未补全",
        "ladder_tags": [],
        "ladder_tag_text": ""
      },
      {
        "actor_name": "姫野ことめ",
        "code": "KAMEF-044",
        "title": "個撮特化 アイドル撮影会 ことみちゃん 町田レンズのBLACK KAMEKO FILE.44 一度センターに立った清楚系アイドルはセンターを維持する為に太ヲタの要求を断れない",
        "author": "",
        "release_date": "2023-08-11",
        "avfan_url": "https://avfan.com/zh-CN/movies/iDfDrufm",
        "page_number": 1,
        "javtxt_enrichment_status": "已补全",
        "javtxt_movie_id": "446053",
        "javtxt_url": "https://javtxt.top/v/446053",
        "javtxt_tags": "口交 偶像艺人 酒店 苗条 美少女 美乳 角色扮演 素人 玩具 女上位 自慰器 中出 第一人称 背部 高清",
        "javtxt_release_date": "2023-08-11",
        "author_raw": "未公开",
        "video_category": "",
        "supplement_enrichment_status": "未补全",
        "ladder_tags": [],
        "ladder_tag_text": ""
      },
      {
        "actor_name": "姫野ことめ",
        "code": "MAXVR-133",
        "title": "VRHQ60fps 制服美少女精选第2辑 -",
        "author": "",
        "release_date": "2023-06-07",
        "avfan_url": "https://avfan.com/zh-CN/movies/EwHSkXZm",
        "page_number": 1,
        "javtxt_enrichment_status": "无搜索结果",
        "javtxt_movie_id": "",
        "javtxt_url": "",
        "javtxt_tags": "",
        "javtxt_release_date": "",
        "author_raw": "",
        "video_category": "",
        "supplement_enrichment_status": "未补全",
        "ladder_tags": [],
        "ladder_tag_text": ""
      },
      {
        "actor_name": "姫野ことめ",
        "code": "KAMEF-019",
        "title": "個撮特化 コスプレ撮影会 ことこちゃん 町田レンズのBLACK KAMEKO FILE.19",
        "author": "",
        "release_date": "2022-11-10",
        "avfan_url": "https://avfan.com/zh-CN/movies/bxHXgl1O",
        "page_number": 1,
        "javtxt_enrichment_status": "已补全",
        "javtxt_movie_id": "423188",
        "javtxt_url": "https://javtxt.top/v/423188",
        "javtxt_tags": "高清 酒店 苗条 美少女 美乳 平胸・微乳 角色扮演 素人 舔阴 女上位 背部 口交 中出 第一人称 接吻 指交 偶像艺人",
        "javtxt_release_date": "2022-11-10",
        "author_raw": "未公开",
        "video_category": "",
        "supplement_enrichment_status": "未补全",
        "ladder_tags": [],
        "ladder_tag_text": ""
      },
      {
        "actor_name": "姫野ことめ",
        "code": "STVF-050",
        "title": "素人パンチラ in 自宅で個人撮影会 vol.050 素人モデル美女4名",
        "author": "",
        "release_date": "2021-11-25",
        "avfan_url": "https://avfan.com/zh-CN/movies/17azZ2K5",
        "page_number": 1,
        "javtxt_enrichment_status": "已补全",
        "javtxt_movie_id": "390027",
        "javtxt_url": "https://javtxt.top/v/390027",
        "javtxt_tags": "高清 赛车女郎 偷拍・偷窥 美少女 角色扮演 巨乳 美乳 底裤偷拍",
        "javtxt_release_date": "2021-11-25",
        "author_raw": "未公开",
        "video_category": "",
        "supplement_enrichment_status": "未补全",
        "ladder_tags": [],
        "ladder_tag_text": ""
      },
      {
        "actor_name": "姫野ことめ",
        "code": "INST-186",
        "title": "ことみ",
        "author": "",
        "release_date": "2021-11-25",
        "avfan_url": "https://avfan.com/zh-CN/movies/A8Ej1zU0",
        "page_number": 1,
        "javtxt_enrichment_status": "已补全",
        "javtxt_movie_id": "390533",
        "javtxt_url": "https://javtxt.top/v/390533",
        "javtxt_tags": "配信専用 素人 第一人称 制服 中出 苗条",
        "javtxt_release_date": "2021-11-25",
        "author_raw": "未公开",
        "video_category": "",
        "supplement_enrichment_status": "未补全",
        "ladder_tags": [],
        "ladder_tag_text": ""
      },
      {
        "actor_name": "姫野ことめ",
        "code": "INST-163",
        "title": "ことこ",
        "author": "",
        "release_date": "2021-09-19",
        "avfan_url": "https://avfan.com/zh-CN/movies/8JGXZiU9",
        "page_number": 1,
        "javtxt_enrichment_status": "已补全",
        "javtxt_movie_id": "385284",
        "javtxt_url": "https://javtxt.top/v/385284",
        "javtxt_tags": "配信専用 素人 第一人称 中出 角色扮演 模特 偶像艺人",
        "javtxt_release_date": "2021-09-19",
        "author_raw": "未公开",
        "video_category": "",
        "supplement_enrichment_status": "未补全",
        "ladder_tags": [],
        "ladder_tag_text": ""
      },
      {
        "actor_name": "姫野ことめ",
        "code": "SHIND-013",
        "title": "跟踪狂M的电车痴汉与住宅侵入记录",
        "author": "",
        "release_date": "2021-08-05",
        "avfan_url": "https://avfan.com/zh-CN/movies/zmOgU4xw",
        "page_number": 1,
        "javtxt_enrichment_status": "无搜索结果",
        "javtxt_movie_id": "",
        "javtxt_url": "",
        "javtxt_tags": "",
        "javtxt_release_date": "",
        "author_raw": "",
        "video_category": "",
        "supplement_enrichment_status": "未补全",
        "ladder_tags": [],
        "ladder_tag_text": ""
      },
      {
        "actor_name": "姫野ことめ",
        "code": "FRIN-025",
        "title": "Kさん",
        "author": "",
        "release_date": "2021-03-26",
        "avfan_url": "https://avfan.com/zh-CN/movies/RkLpzYgG",
        "page_number": 1,
        "javtxt_enrichment_status": "已补全",
        "javtxt_movie_id": "377272",
        "javtxt_url": "https://javtxt.top/v/377272",
        "javtxt_tags": "配信専用 素人 中出 苗条 美少女 投稿 偶像艺人",
        "javtxt_release_date": "2021-03-26",
        "author_raw": "未公开",
        "video_category": "",
        "supplement_enrichment_status": "未补全",
        "ladder_tags": [],
        "ladder_tag_text": ""
      },
      {
        "actor_name": "姫野ことめ",
        "code": "HUNTA-969",
        "title": "「秘密にしてくれるなら、私のこと好きにしていいよ…。」登校拒否のボクだけが知っている超マジメな学級委員長のむっつりスケベな本性！登校拒否の…",
        "author": "",
        "release_date": "2021-03-18",
        "avfan_url": "https://avfan.com/zh-CN/movies/cPMuyj3C",
        "page_number": 1,
        "javtxt_enrichment_status": "已补全",
        "javtxt_movie_id": "338377",
        "javtxt_url": "https://javtxt.top/v/338377",
        "javtxt_tags": "高清 独家分发 女子校生 中出 学生服 女色情狂 眼镜",
        "javtxt_release_date": "2021-03-18",
        "author_raw": "未公开",
        "video_category": "",
        "supplement_enrichment_status": "未补全",
        "ladder_tags": [],
        "ladder_tag_text": ""
      },
      {
        "actor_name": "姫野ことめ",
        "code": "ZKWD-016",
        "title": "放課後肉便器16人目",
        "author": "柳瀬みわ",
        "release_date": "2021-01-24",
        "avfan_url": "https://avfan.com/zh-CN/movies/NQQyuWgU",
        "page_number": 2,
        "javtxt_enrichment_status": "已补全",
        "javtxt_movie_id": "335071",
        "javtxt_url": "https://javtxt.top/v/335071",
        "javtxt_tags": "舞蹈 中出 深喉 颜射 学校泳装・死库水 单体作品 独家分发 高清",
        "javtxt_release_date": "2021-01-24",
        "author_raw": "柳瀬みわ",
        "video_category": "单体作品",
        "supplement_enrichment_status": "未补全",
        "ladder_tags": [],
        "ladder_tag_text": ""
      },
      {
        "actor_name": "姫野ことめ",
        "code": "SHINKI-025",
        "title": "K25ちゃん",
        "author": "",
        "release_date": "2021-01-22",
        "avfan_url": "https://avfan.com/zh-CN/movies/416QBv7k",
        "page_number": 2,
        "javtxt_enrichment_status": "已补全",
        "javtxt_movie_id": "378565",
        "javtxt_url": "https://javtxt.top/v/378565",
        "javtxt_tags": "颜射 痴漢 手マン パンチラモノ 偷拍・偷窥 中出 制服 素人 配信専用",
        "javtxt_release_date": "2021-01-22",
        "author_raw": "未公开",
        "video_category": "",
        "supplement_enrichment_status": "未补全",
        "ladder_tags": [],
        "ladder_tag_text": ""
      },
      {
        "actor_name": "姫野ことめ",
        "code": "MDBK-140",
        "title": "ミニスカTバック女子校生",
        "author": "",
        "release_date": "2020-11-13",
        "avfan_url": "https://avfan.com/zh-CN/movies/EMGdYXZm",
        "page_number": 2,
        "javtxt_enrichment_status": "无搜索结果",
        "javtxt_movie_id": "",
        "javtxt_url": "",
        "javtxt_tags": "",
        "javtxt_release_date": "",
        "author_raw": "",
        "video_category": "共演作品",
        "supplement_enrichment_status": "未补全",
        "ladder_tags": [],
        "ladder_tag_text": ""
      },
      {
        "actor_name": "姫野ことめ",
        "code": "MXX-79",
        "title": "Mercy Beaucoup MXX 79 -",
        "author": "",
        "release_date": "2020-11-03",
        "avfan_url": "https://avfan.com/zh-CN/movies/3nrF4Ech",
        "page_number": 2,
        "javtxt_enrichment_status": "无搜索结果",
        "javtxt_movie_id": "",
        "javtxt_url": "",
        "javtxt_tags": "",
        "javtxt_release_date": "",
        "author_raw": "",
        "video_category": "",
        "supplement_enrichment_status": "未补全",
        "ladder_tags": [],
        "ladder_tag_text": ""
      },
      {
        "actor_name": "姫野ことめ",
        "code": "OPCYN-115",
        "title": "ことめ",
        "author": "",
        "release_date": "2020-10-28",
        "avfan_url": "https://avfan.com/zh-CN/movies/gXZX6eTl",
        "page_number": 2,
        "javtxt_enrichment_status": "已补全",
        "javtxt_movie_id": "373821",
        "javtxt_url": "https://javtxt.top/v/373821",
        "javtxt_tags": "配信専用 素人 人妻 不伦 中出 女色情狂",
        "javtxt_release_date": "2020-10-28",
        "author_raw": "未公开",
        "video_category": "",
        "supplement_enrichment_status": "未补全",
        "ladder_tags": [],
        "ladder_tag_text": ""
      },
      {
        "actor_name": "姫野ことめ",
        "code": "SUPA-544",
        "title": "真面目で堅物そうな休憩中のリケジョ研究員がターゲット！性に対して関心が無いように見えて実は全員むっつりドスケベ！？チ●ポを出されると研究対象のように観察・触診してフェラチオまで！もう興奮してグチョグチョのオマ●コは体育会系チ●ポを拒めない！223分SP",
        "author": "",
        "release_date": "2020-10-09",
        "avfan_url": "https://avfan.com/zh-CN/movies/Ai8S1zU0",
        "page_number": 2,
        "javtxt_enrichment_status": "已补全",
        "javtxt_movie_id": "326240",
        "javtxt_url": "https://javtxt.top/v/326240",
        "javtxt_tags": "高清 眼镜 中出 企画 搭讪 素人",
        "javtxt_release_date": "2020-10-09",
        "author_raw": "未公开",
        "video_category": "",
        "supplement_enrichment_status": "未补全",
        "ladder_tags": [],
        "ladder_tag_text": ""
      },
      {
        "actor_name": "姫野ことめ",
        "code": "ORE-713",
        "title": "ことめ研究員",
        "author": "",
        "release_date": "2020-10-08",
        "avfan_url": "https://avfan.com/zh-CN/movies/P5C0sr1D",
        "page_number": 2,
        "javtxt_enrichment_status": "无搜索结果",
        "javtxt_movie_id": "",
        "javtxt_url": "",
        "javtxt_tags": "",
        "javtxt_release_date": "",
        "author_raw": "",
        "video_category": "",
        "supplement_enrichment_status": "未补全",
        "ladder_tags": [],
        "ladder_tag_text": ""
      },
      {
        "actor_name": "姫野ことめ",
        "code": "OVG-149",
        "title": "挑発！ナマイキ娘のパンチラ足コキ3",
        "author": "",
        "release_date": "2020-08-19",
        "avfan_url": "https://avfan.com/zh-CN/movies/8DDU8iU9",
        "page_number": 2,
        "javtxt_enrichment_status": "无搜索结果",
        "javtxt_movie_id": "",
        "javtxt_url": "",
        "javtxt_tags": "高清 足交 底裤偷拍 水手服 痴女 女子校生",
        "javtxt_release_date": "2020-08-19",
        "author_raw": "",
        "video_category": "合集作品",
        "supplement_enrichment_status": "未补全",
        "ladder_tags": [],
        "ladder_tag_text": ""
      },
      {
        "actor_name": "姫野ことめ",
        "code": "GVH-096",
        "title": "WNTR恐ろしいほど女に汚い先輩に自慢の美人母と可愛い妹を性玩具にされた悪夢",
        "author": "小早川怜子 姫野ことめ",
        "release_date": "2020-07-22",
        "avfan_url": "https://avfan.com/zh-CN/movies/xLFy0fWQ",
        "page_number": 2,
        "javtxt_enrichment_status": "已补全",
        "javtxt_movie_id": "321021",
        "javtxt_url": "https://javtxt.top/v/321021",
        "javtxt_tags": "高清 巨乳 姐・妹 人妻・主妇 戏剧 绿帽子・NTR",
        "javtxt_release_date": "2020-07-22",
        "author_raw": "小早川怜子 姫野ことめ",
        "video_category": "共演作品",
        "supplement_enrichment_status": "未补全",
        "ladder_tags": [],
        "ladder_tag_text": ""
      },
      {
        "actor_name": "姫野ことめ",
        "code": "APNS-196",
        "title": "姬野琴目（DOD）-",
        "author": "姫野ことめ",
        "release_date": "2020-07-20",
        "avfan_url": "https://avfan.com/zh-CN/movies/vSDw0imX",
        "page_number": 1,
        "javtxt_enrichment_status": "已补全",
        "javtxt_movie_id": "320895",
        "javtxt_url": "https://javtxt.top/v/320895",
        "javtxt_tags": "高清 独家分发 单体作品 中出 颜射 女子校生 3P・4P 戏剧",
        "javtxt_release_date": "2020-07-20",
        "author_raw": "姫野ことめ",
        "video_category": "单体作品",
        "supplement_enrichment_status": "未补全",
        "ladder_tags": [],
        "ladder_tag_text": ""
      },
      {
        "actor_name": "姫野ことめ",
        "code": "OREC-553",
        "title": "ことめ",
        "author": "",
        "release_date": "2020-07-13",
        "avfan_url": "https://avfan.com/zh-CN/movies/NB1I4WgU",
        "page_number": 2,
        "javtxt_enrichment_status": "已补全",
        "javtxt_movie_id": "372762",
        "javtxt_url": "https://javtxt.top/v/372762",
        "javtxt_tags": "配信専用 素人 搭讪 美少女 童贞",
        "javtxt_release_date": "2020-07-13",
        "author_raw": "未公开",
        "video_category": "",
        "supplement_enrichment_status": "未补全",
        "ladder_tags": [],
        "ladder_tag_text": ""
      },
      {
        "actor_name": "姫野ことめ",
        "code": "NAMA-090",
        "title": "332NAMA-090",
        "author": "",
        "release_date": "2020-07-13",
        "avfan_url": "https://avfan.com/zh-CN/movies/38uAEchq",
        "page_number": 2,
        "javtxt_enrichment_status": "已补全",
        "javtxt_movie_id": "372765",
        "javtxt_url": "https://javtxt.top/v/372765",
        "javtxt_tags": "独家分发 配信専用 素人 第一人称 苗条 自慰器 美乳 美尻 中出 口内射精",
        "javtxt_release_date": "2020-07-13",
        "author_raw": "未公开",
        "video_category": "",
        "supplement_enrichment_status": "未补全",
        "ladder_tags": [],
        "ladder_tag_text": ""
      },
      {
        "actor_name": "姫野ことめ",
        "code": "APKH-147",
        "title": "【凄い腰ツキのペット娘】華奢美少女を飼って籠ってぬっぽり過激性交ハメ撮り",
        "author": "姫野ことめ",
        "release_date": "2020-07-12",
        "avfan_url": "https://avfan.com/zh-CN/movies/f54F5PiU",
        "page_number": 2,
        "javtxt_enrichment_status": "已补全",
        "javtxt_movie_id": "320429",
        "javtxt_url": "https://javtxt.top/v/320429",
        "javtxt_tags": "高清 独家分发 女子校生 单体作品 中出 苗条 第一人称 颜射",
        "javtxt_release_date": "2020-07-12",
        "author_raw": "姫野ことめ",
        "video_category": "单体作品",
        "supplement_enrichment_status": "未补全",
        "ladder_tags": [],
        "ladder_tag_text": ""
      },
      {
        "actor_name": "姫野ことめ",
        "code": "MKON-032",
        "title": "清纯可爱的图书委员女友怎么可能是隐藏的荡妇！姬野琴目",
        "author": "姫野ことめ",
        "release_date": "2020-07-05",
        "avfan_url": "https://avfan.com/zh-CN/movies/aJ2OdVTi",
        "page_number": 1,
        "javtxt_enrichment_status": "已补全",
        "javtxt_movie_id": "319978",
        "javtxt_url": "https://javtxt.top/v/319978",
        "javtxt_tags": "单体作品 妄想族 中出 3P・4P 学生服 女子校生 独家分发 高清 绿帽子・NTR",
        "javtxt_release_date": "2020-07-05",
        "author_raw": "姫野ことめ",
        "video_category": "单体作品",
        "supplement_enrichment_status": "未补全",
        "ladder_tags": [],
        "ladder_tag_text": ""
      },
      {
        "actor_name": "姫野ことめ",
        "code": "DAC-011",
        "title": "どっく あまちゅあ ちゃんねる",
        "author": "",
        "release_date": "2020-06-12",
        "avfan_url": "https://avfan.com/zh-CN/movies/v2TP70im",
        "page_number": 2,
        "javtxt_enrichment_status": "已补全",
        "javtxt_movie_id": "318334",
        "javtxt_url": "https://javtxt.top/v/318334",
        "javtxt_tags": "高清 第一人称 中出 素人",
        "javtxt_release_date": "2020-06-12",
        "author_raw": "未公开",
        "video_category": "",
        "supplement_enrichment_status": "未补全",
        "ladder_tags": [],
        "ladder_tag_text": ""
      },
      {
        "actor_name": "姫野ことめ",
        "code": "SVDVD-800",
        "title": "将电压调至86倍的超强震动棒塞入阴道，被牵着在街上强制高潮散步！",
        "author": "",
        "release_date": "2020-06-11",
        "avfan_url": "https://avfan.com/zh-CN/movies/xEFlfWQw",
        "page_number": 2,
        "javtxt_enrichment_status": "已补全",
        "javtxt_movie_id": "318297",
        "javtxt_url": "https://javtxt.top/v/318297",
        "javtxt_tags": "高清 浴室 野外・露出 跳蛋 搭讪 羞耻 トリプルHAPPY30％OFFセール第3弾",
        "javtxt_release_date": "2020-06-11",
        "author_raw": "未公开",
        "video_category": "共演作品",
        "supplement_enrichment_status": "未补全",
        "ladder_tags": [],
        "ladder_tag_text": ""
      },
      {
        "actor_name": "姫野ことめ",
        "code": "LAS-018",
        "title": "ことめちゃん",
        "author": "",
        "release_date": "2020-05-18",
        "avfan_url": "https://avfan.com/zh-CN/movies/TCmyXN2p",
        "page_number": 2,
        "javtxt_enrichment_status": "已补全",
        "javtxt_movie_id": "372302",
        "javtxt_url": "https://javtxt.top/v/372302",
        "javtxt_tags": "配信専用 素人 搭讪 童顔 オモチャ",
        "javtxt_release_date": "2020-05-18",
        "author_raw": "未公开",
        "video_category": "",
        "supplement_enrichment_status": "未补全",
        "ladder_tags": [],
        "ladder_tag_text": ""
      },
      {
        "actor_name": "姫野ことめ",
        "code": "BIG-063",
        "title": "ことみ",
        "author": "",
        "release_date": "2020-05-07",
        "avfan_url": "https://avfan.com/zh-CN/movies/cPTJgj3C",
        "page_number": 2,
        "javtxt_enrichment_status": "已补全",
        "javtxt_movie_id": "372206",
        "javtxt_url": "https://javtxt.top/v/372206",
        "javtxt_tags": "配信専用 素人 中出 鬼畜 制服 童顔 潮吹",
        "javtxt_release_date": "2020-05-07",
        "author_raw": "未公开",
        "video_category": "",
        "supplement_enrichment_status": "未补全",
        "ladder_tags": [],
        "ladder_tag_text": ""
      },
      {
        "actor_name": "姫野ことめ",
        "code": "BBAN-278",
        "title": "絶対服従 いいなりメイド レズビアン調教 ～奴●メイドの館～ 姫野ことめ",
        "author": "姫野ことめ 澤村レイコ",
        "release_date": "2020-05-02",
        "avfan_url": "https://avfan.com/zh-CN/movies/gX9faeTl",
        "page_number": 3,
        "javtxt_enrichment_status": "已补全",
        "javtxt_movie_id": "315868",
        "javtxt_url": "https://javtxt.top/v/315868",
        "javtxt_tags": "高清 独家分发 美少女 女同 女仆 同性接吻",
        "javtxt_release_date": "2020-05-02",
        "author_raw": "姫野ことめ 澤村レイコ",
        "video_category": "共演作品",
        "supplement_enrichment_status": "未补全",
        "ladder_tags": [
          "仙徐娘",
          "绾青瀑",
          "楚腰轻",
          "凝霜雪"
        ],
        "ladder_tag_text": "仙徐娘 | 绾青瀑 | 楚腰轻 | 凝霜雪"
      },
      {
        "actor_name": "姫野ことめ",
        "code": "MFC-003",
        "title": "ことめ",
        "author": "",
        "release_date": "2020-04-22",
        "avfan_url": "https://avfan.com/zh-CN/movies/nybgvwHD",
        "page_number": 3,
        "javtxt_enrichment_status": "已补全",
        "javtxt_movie_id": "372052",
        "javtxt_url": "https://javtxt.top/v/372052",
        "javtxt_tags": "按摩棒 オモチャ 自慰器 童顔 清楚 女大学生 第一人称 素人 配信専用",
        "javtxt_release_date": "2020-04-22",
        "author_raw": "未公开",
        "video_category": "",
        "supplement_enrichment_status": "未补全",
        "ladder_tags": [],
        "ladder_tag_text": ""
      },
      {
        "actor_name": "姫野ことめ",
        "code": "SIRO-4115",
        "title": "首次拍摄 - 无法控制高潮的少女 - 19岁女大学生。一位以读书为爱好的认真19岁少女登场。她说着'从没和这么年长的人...'。※由于女孩反应强烈，建议使用耳机观看。素人应募，首次成人影片拍摄",
        "author": "",
        "release_date": "2020-04-14",
        "avfan_url": "https://avfan.com/zh-CN/movies/NDtOWgUj",
        "page_number": 3,
        "javtxt_enrichment_status": "已补全",
        "javtxt_movie_id": "371970",
        "javtxt_url": "https://javtxt.top/v/371970",
        "javtxt_tags": "独家分发 配信専用 素人 初撮り 第一人称 女大学生 苗条 美尻 颜射",
        "javtxt_release_date": "2020-04-14",
        "author_raw": "未公开",
        "video_category": "",
        "supplement_enrichment_status": "未补全",
        "ladder_tags": [],
        "ladder_tag_text": ""
      },
      {
        "actor_name": "姫野ことめ",
        "code": "ATID-409",
        "title": "恥辱の教育実習生17",
        "author": "姫野ことめ",
        "release_date": "2020-04-04",
        "avfan_url": "https://avfan.com/zh-CN/movies/dWrCXkDF",
        "page_number": 3,
        "javtxt_enrichment_status": "已补全",
        "javtxt_movie_id": "313951",
        "javtxt_url": "https://javtxt.top/v/313951",
        "javtxt_tags": "独家分发 高清 耻辱 女教师 女大学生 单体作品",
        "javtxt_release_date": "2020-04-04",
        "author_raw": "姫野ことめ",
        "video_category": "单体作品",
        "supplement_enrichment_status": "未补全",
        "ladder_tags": [],
        "ladder_tag_text": ""
      },
      {
        "actor_name": "姫野ことめ",
        "code": "ADN-237",
        "title": "大学受験の当日、私はハゲオヤジに犯●れました…。",
        "author": "",
        "release_date": "2020-02-01",
        "avfan_url": "https://avfan.com/zh-CN/movies/pAg7N6Jw",
        "page_number": 3,
        "javtxt_enrichment_status": "无搜索结果",
        "javtxt_movie_id": "",
        "javtxt_url": "",
        "javtxt_tags": "",
        "javtxt_release_date": "",
        "author_raw": "",
        "video_category": "共演作品",
        "supplement_enrichment_status": "未补全",
        "ladder_tags": [],
        "ladder_tag_text": ""
      }
    ],
    "eligible_web_movies": [
      {
        "actor_name": "姫野ことめ",
        "code": "TCNB-062",
        "title": "ともか",
        "author": "",
        "release_date": "2025-08-08",
        "avfan_url": "https://avfan.com/zh-CN/movies/9KCwHAg9",
        "page_number": 1,
        "javtxt_enrichment_status": "无搜索结果",
        "javtxt_movie_id": "",
        "javtxt_url": "",
        "javtxt_tags": "",
        "javtxt_release_date": "",
        "author_raw": "",
        "video_category": "",
        "supplement_enrichment_status": "未补全",
        "ladder_tags": [],
        "ladder_tag_text": ""
      },
      {
        "actor_name": "姫野ことめ",
        "code": "TCNB-022",
        "title": "ともか",
        "author": "",
        "release_date": "2024-11-01",
        "avfan_url": "https://avfan.com/zh-CN/movies/enA6b3Fj",
        "page_number": 1,
        "javtxt_enrichment_status": "无搜索结果",
        "javtxt_movie_id": "",
        "javtxt_url": "",
        "javtxt_tags": "",
        "javtxt_release_date": "",
        "author_raw": "",
        "video_category": "",
        "supplement_enrichment_status": "未补全",
        "ladder_tags": [],
        "ladder_tag_text": ""
      },
      {
        "actor_name": "姫野ことめ",
        "code": "CLO-325",
        "title": "人気の無くなった学校で、あの娘と…。",
        "author": "姫野ことめ",
        "release_date": "2024-05-10",
        "avfan_url": "https://avfan.com/zh-CN/movies/r41ymLv1",
        "page_number": 1,
        "javtxt_enrichment_status": "已补全",
        "javtxt_movie_id": "471633",
        "javtxt_url": "https://javtxt.top/v/471633",
        "javtxt_tags": "高清 单体作品 口交 指交 水手服 女子校生 美少女",
        "javtxt_release_date": "2024-05-10",
        "author_raw": "姫野ことめ",
        "video_category": "单体作品",
        "supplement_enrichment_status": "未补全",
        "ladder_tags": [],
        "ladder_tag_text": ""
      },
      {
        "actor_name": "姫野ことめ",
        "code": "KWBD-361",
        "title": "可爱女孩激情高潮！同步绝顶的最后冲刺正常位内射105连发",
        "author": "",
        "release_date": "2023-12-29",
        "avfan_url": "https://avfan.com/zh-CN/movies/fVtnPiUO",
        "page_number": 1,
        "javtxt_enrichment_status": "无搜索结果",
        "javtxt_movie_id": "",
        "javtxt_url": "",
        "javtxt_tags": "",
        "javtxt_release_date": "2023-12-29",
        "author_raw": "",
        "video_category": "合集作品",
        "supplement_enrichment_status": "未补全",
        "ladder_tags": [],
        "ladder_tag_text": ""
      },
      {
        "actor_name": "姫野ことめ",
        "code": "VOSM-054",
        "title": "VRHQ剧超高画质500分钟！深情对视＆亲密互动中正常体位下可爱脸蛋尽情观赏！无限快感！精选55位女优",
        "author": "",
        "release_date": "2023-12-01",
        "avfan_url": "https://avfan.com/zh-CN/movies/L4clcOzh",
        "page_number": 1,
        "javtxt_enrichment_status": "无搜索结果",
        "javtxt_movie_id": "",
        "javtxt_url": "",
        "javtxt_tags": "",
        "javtxt_release_date": "",
        "author_raw": "",
        "video_category": "",
        "supplement_enrichment_status": "未补全",
        "ladder_tags": [],
        "ladder_tag_text": ""
      },
      {
        "actor_name": "姫野ことめ",
        "code": "MDBK-312",
        "title": "大量内射 -",
        "author": "",
        "release_date": "2023-11-28",
        "avfan_url": "https://avfan.com/zh-CN/movies/AI7YzU0g",
        "page_number": 1,
        "javtxt_enrichment_status": "无搜索结果",
        "javtxt_movie_id": "",
        "javtxt_url": "",
        "javtxt_tags": "",
        "javtxt_release_date": "",
        "author_raw": "",
        "video_category": "共演作品",
        "supplement_enrichment_status": "未补全",
        "ladder_tags": [],
        "ladder_tag_text": ""
      },
      {
        "actor_name": "姫野ことめ",
        "code": "KAMEF-044",
        "title": "個撮特化 アイドル撮影会 ことみちゃん 町田レンズのBLACK KAMEKO FILE.44 一度センターに立った清楚系アイドルはセンターを維持する為に太ヲタの要求を断れない",
        "author": "",
        "release_date": "2023-08-11",
        "avfan_url": "https://avfan.com/zh-CN/movies/iDfDrufm",
        "page_number": 1,
        "javtxt_enrichment_status": "已补全",
        "javtxt_movie_id": "446053",
        "javtxt_url": "https://javtxt.top/v/446053",
        "javtxt_tags": "口交 偶像艺人 酒店 苗条 美少女 美乳 角色扮演 素人 玩具 女上位 自慰器 中出 第一人称 背部 高清",
        "javtxt_release_date": "2023-08-11",
        "author_raw": "未公开",
        "video_category": "",
        "supplement_enrichment_status": "未补全",
        "ladder_tags": [],
        "ladder_tag_text": ""
      },
      {
        "actor_name": "姫野ことめ",
        "code": "MAXVR-133",
        "title": "VRHQ60fps 制服美少女精选第2辑 -",
        "author": "",
        "release_date": "2023-06-07",
        "avfan_url": "https://avfan.com/zh-CN/movies/EwHSkXZm",
        "page_number": 1,
        "javtxt_enrichment_status": "无搜索结果",
        "javtxt_movie_id": "",
        "javtxt_url": "",
        "javtxt_tags": "",
        "javtxt_release_date": "",
        "author_raw": "",
        "video_category": "",
        "supplement_enrichment_status": "未补全",
        "ladder_tags": [],
        "ladder_tag_text": ""
      },
      {
        "actor_name": "姫野ことめ",
        "code": "KAMEF-019",
        "title": "個撮特化 コスプレ撮影会 ことこちゃん 町田レンズのBLACK KAMEKO FILE.19",
        "author": "",
        "release_date": "2022-11-10",
        "avfan_url": "https://avfan.com/zh-CN/movies/bxHXgl1O",
        "page_number": 1,
        "javtxt_enrichment_status": "已补全",
        "javtxt_movie_id": "423188",
        "javtxt_url": "https://javtxt.top/v/423188",
        "javtxt_tags": "高清 酒店 苗条 美少女 美乳 平胸・微乳 角色扮演 素人 舔阴 女上位 背部 口交 中出 第一人称 接吻 指交 偶像艺人",
        "javtxt_release_date": "2022-11-10",
        "author_raw": "未公开",
        "video_category": "",
        "supplement_enrichment_status": "未补全",
        "ladder_tags": [],
        "ladder_tag_text": ""
      },
      {
        "actor_name": "姫野ことめ",
        "code": "STVF-050",
        "title": "素人パンチラ in 自宅で個人撮影会 vol.050 素人モデル美女4名",
        "author": "",
        "release_date": "2021-11-25",
        "avfan_url": "https://avfan.com/zh-CN/movies/17azZ2K5",
        "page_number": 1,
        "javtxt_enrichment_status": "已补全",
        "javtxt_movie_id": "390027",
        "javtxt_url": "https://javtxt.top/v/390027",
        "javtxt_tags": "高清 赛车女郎 偷拍・偷窥 美少女 角色扮演 巨乳 美乳 底裤偷拍",
        "javtxt_release_date": "2021-11-25",
        "author_raw": "未公开",
        "video_category": "",
        "supplement_enrichment_status": "未补全",
        "ladder_tags": [],
        "ladder_tag_text": ""
      },
      {
        "actor_name": "姫野ことめ",
        "code": "INST-186",
        "title": "ことみ",
        "author": "",
        "release_date": "2021-11-25",
        "avfan_url": "https://avfan.com/zh-CN/movies/A8Ej1zU0",
        "page_number": 1,
        "javtxt_enrichment_status": "已补全",
        "javtxt_movie_id": "390533",
        "javtxt_url": "https://javtxt.top/v/390533",
        "javtxt_tags": "配信専用 素人 第一人称 制服 中出 苗条",
        "javtxt_release_date": "2021-11-25",
        "author_raw": "未公开",
        "video_category": "",
        "supplement_enrichment_status": "未补全",
        "ladder_tags": [],
        "ladder_tag_text": ""
      },
      {
        "actor_name": "姫野ことめ",
        "code": "INST-163",
        "title": "ことこ",
        "author": "",
        "release_date": "2021-09-19",
        "avfan_url": "https://avfan.com/zh-CN/movies/8JGXZiU9",
        "page_number": 1,
        "javtxt_enrichment_status": "已补全",
        "javtxt_movie_id": "385284",
        "javtxt_url": "https://javtxt.top/v/385284",
        "javtxt_tags": "配信専用 素人 第一人称 中出 角色扮演 模特 偶像艺人",
        "javtxt_release_date": "2021-09-19",
        "author_raw": "未公开",
        "video_category": "",
        "supplement_enrichment_status": "未补全",
        "ladder_tags": [],
        "ladder_tag_text": ""
      },
      {
        "actor_name": "姫野ことめ",
        "code": "SHIND-013",
        "title": "跟踪狂M的电车痴汉与住宅侵入记录",
        "author": "",
        "release_date": "2021-08-05",
        "avfan_url": "https://avfan.com/zh-CN/movies/zmOgU4xw",
        "page_number": 1,
        "javtxt_enrichment_status": "无搜索结果",
        "javtxt_movie_id": "",
        "javtxt_url": "",
        "javtxt_tags": "",
        "javtxt_release_date": "",
        "author_raw": "",
        "video_category": "",
        "supplement_enrichment_status": "未补全",
        "ladder_tags": [],
        "ladder_tag_text": ""
      },
      {
        "actor_name": "姫野ことめ",
        "code": "FRIN-025",
        "title": "Kさん",
        "author": "",
        "release_date": "2021-03-26",
        "avfan_url": "https://avfan.com/zh-CN/movies/RkLpzYgG",
        "page_number": 1,
        "javtxt_enrichment_status": "已补全",
        "javtxt_movie_id": "377272",
        "javtxt_url": "https://javtxt.top/v/377272",
        "javtxt_tags": "配信専用 素人 中出 苗条 美少女 投稿 偶像艺人",
        "javtxt_release_date": "2021-03-26",
        "author_raw": "未公开",
        "video_category": "",
        "supplement_enrichment_status": "未补全",
        "ladder_tags": [],
        "ladder_tag_text": ""
      },
      {
        "actor_name": "姫野ことめ",
        "code": "HUNTA-969",
        "title": "「秘密にしてくれるなら、私のこと好きにしていいよ…。」登校拒否のボクだけが知っている超マジメな学級委員長のむっつりスケベな本性！登校拒否の…",
        "author": "",
        "release_date": "2021-03-18",
        "avfan_url": "https://avfan.com/zh-CN/movies/cPMuyj3C",
        "page_number": 1,
        "javtxt_enrichment_status": "已补全",
        "javtxt_movie_id": "338377",
        "javtxt_url": "https://javtxt.top/v/338377",
        "javtxt_tags": "高清 独家分发 女子校生 中出 学生服 女色情狂 眼镜",
        "javtxt_release_date": "2021-03-18",
        "author_raw": "未公开",
        "video_category": "",
        "supplement_enrichment_status": "未补全",
        "ladder_tags": [],
        "ladder_tag_text": ""
      },
      {
        "actor_name": "姫野ことめ",
        "code": "ZKWD-016",
        "title": "放課後肉便器16人目",
        "author": "柳瀬みわ",
        "release_date": "2021-01-24",
        "avfan_url": "https://avfan.com/zh-CN/movies/NQQyuWgU",
        "page_number": 2,
        "javtxt_enrichment_status": "已补全",
        "javtxt_movie_id": "335071",
        "javtxt_url": "https://javtxt.top/v/335071",
        "javtxt_tags": "舞蹈 中出 深喉 颜射 学校泳装・死库水 单体作品 独家分发 高清",
        "javtxt_release_date": "2021-01-24",
        "author_raw": "柳瀬みわ",
        "video_category": "单体作品",
        "supplement_enrichment_status": "未补全",
        "ladder_tags": [],
        "ladder_tag_text": ""
      },
      {
        "actor_name": "姫野ことめ",
        "code": "SHINKI-025",
        "title": "K25ちゃん",
        "author": "",
        "release_date": "2021-01-22",
        "avfan_url": "https://avfan.com/zh-CN/movies/416QBv7k",
        "page_number": 2,
        "javtxt_enrichment_status": "已补全",
        "javtxt_movie_id": "378565",
        "javtxt_url": "https://javtxt.top/v/378565",
        "javtxt_tags": "颜射 痴漢 手マン パンチラモノ 偷拍・偷窥 中出 制服 素人 配信専用",
        "javtxt_release_date": "2021-01-22",
        "author_raw": "未公开",
        "video_category": "",
        "supplement_enrichment_status": "未补全",
        "ladder_tags": [],
        "ladder_tag_text": ""
      },
      {
        "actor_name": "姫野ことめ",
        "code": "MDBK-140",
        "title": "ミニスカTバック女子校生",
        "author": "",
        "release_date": "2020-11-13",
        "avfan_url": "https://avfan.com/zh-CN/movies/EMGdYXZm",
        "page_number": 2,
        "javtxt_enrichment_status": "无搜索结果",
        "javtxt_movie_id": "",
        "javtxt_url": "",
        "javtxt_tags": "",
        "javtxt_release_date": "",
        "author_raw": "",
        "video_category": "共演作品",
        "supplement_enrichment_status": "未补全",
        "ladder_tags": [],
        "ladder_tag_text": ""
      },
      {
        "actor_name": "姫野ことめ",
        "code": "MXX-79",
        "title": "Mercy Beaucoup MXX 79 -",
        "author": "",
        "release_date": "2020-11-03",
        "avfan_url": "https://avfan.com/zh-CN/movies/3nrF4Ech",
        "page_number": 2,
        "javtxt_enrichment_status": "无搜索结果",
        "javtxt_movie_id": "",
        "javtxt_url": "",
        "javtxt_tags": "",
        "javtxt_release_date": "",
        "author_raw": "",
        "video_category": "",
        "supplement_enrichment_status": "未补全",
        "ladder_tags": [],
        "ladder_tag_text": ""
      },
      {
        "actor_name": "姫野ことめ",
        "code": "OPCYN-115",
        "title": "ことめ",
        "author": "",
        "release_date": "2020-10-28",
        "avfan_url": "https://avfan.com/zh-CN/movies/gXZX6eTl",
        "page_number": 2,
        "javtxt_enrichment_status": "已补全",
        "javtxt_movie_id": "373821",
        "javtxt_url": "https://javtxt.top/v/373821",
        "javtxt_tags": "配信専用 素人 人妻 不伦 中出 女色情狂",
        "javtxt_release_date": "2020-10-28",
        "author_raw": "未公开",
        "video_category": "",
        "supplement_enrichment_status": "未补全",
        "ladder_tags": [],
        "ladder_tag_text": ""
      },
      {
        "actor_name": "姫野ことめ",
        "code": "SUPA-544",
        "title": "真面目で堅物そうな休憩中のリケジョ研究員がターゲット！性に対して関心が無いように見えて実は全員むっつりドスケベ！？チ●ポを出されると研究対象のように観察・触診してフェラチオまで！もう興奮してグチョグチョのオマ●コは体育会系チ●ポを拒めない！223分SP",
        "author": "",
        "release_date": "2020-10-09",
        "avfan_url": "https://avfan.com/zh-CN/movies/Ai8S1zU0",
        "page_number": 2,
        "javtxt_enrichment_status": "已补全",
        "javtxt_movie_id": "326240",
        "javtxt_url": "https://javtxt.top/v/326240",
        "javtxt_tags": "高清 眼镜 中出 企画 搭讪 素人",
        "javtxt_release_date": "2020-10-09",
        "author_raw": "未公开",
        "video_category": "",
        "supplement_enrichment_status": "未补全",
        "ladder_tags": [],
        "ladder_tag_text": ""
      },
      {
        "actor_name": "姫野ことめ",
        "code": "ORE-713",
        "title": "ことめ研究員",
        "author": "",
        "release_date": "2020-10-08",
        "avfan_url": "https://avfan.com/zh-CN/movies/P5C0sr1D",
        "page_number": 2,
        "javtxt_enrichment_status": "无搜索结果",
        "javtxt_movie_id": "",
        "javtxt_url": "",
        "javtxt_tags": "",
        "javtxt_release_date": "",
        "author_raw": "",
        "video_category": "",
        "supplement_enrichment_status": "未补全",
        "ladder_tags": [],
        "ladder_tag_text": ""
      },
      {
        "actor_name": "姫野ことめ",
        "code": "OVG-149",
        "title": "挑発！ナマイキ娘のパンチラ足コキ3",
        "author": "",
        "release_date": "2020-08-19",
        "avfan_url": "https://avfan.com/zh-CN/movies/8DDU8iU9",
        "page_number": 2,
        "javtxt_enrichment_status": "无搜索结果",
        "javtxt_movie_id": "",
        "javtxt_url": "",
        "javtxt_tags": "高清 足交 底裤偷拍 水手服 痴女 女子校生",
        "javtxt_release_date": "2020-08-19",
        "author_raw": "",
        "video_category": "合集作品",
        "supplement_enrichment_status": "未补全",
        "ladder_tags": [],
        "ladder_tag_text": ""
      },
      {
        "actor_name": "姫野ことめ",
        "code": "GVH-096",
        "title": "WNTR恐ろしいほど女に汚い先輩に自慢の美人母と可愛い妹を性玩具にされた悪夢",
        "author": "小早川怜子 姫野ことめ",
        "release_date": "2020-07-22",
        "avfan_url": "https://avfan.com/zh-CN/movies/xLFy0fWQ",
        "page_number": 2,
        "javtxt_enrichment_status": "已补全",
        "javtxt_movie_id": "321021",
        "javtxt_url": "https://javtxt.top/v/321021",
        "javtxt_tags": "高清 巨乳 姐・妹 人妻・主妇 戏剧 绿帽子・NTR",
        "javtxt_release_date": "2020-07-22",
        "author_raw": "小早川怜子 姫野ことめ",
        "video_category": "共演作品",
        "supplement_enrichment_status": "未补全",
        "ladder_tags": [],
        "ladder_tag_text": ""
      },
      {
        "actor_name": "姫野ことめ",
        "code": "APNS-196",
        "title": "姬野琴目（DOD）-",
        "author": "姫野ことめ",
        "release_date": "2020-07-20",
        "avfan_url": "https://avfan.com/zh-CN/movies/vSDw0imX",
        "page_number": 1,
        "javtxt_enrichment_status": "已补全",
        "javtxt_movie_id": "320895",
        "javtxt_url": "https://javtxt.top/v/320895",
        "javtxt_tags": "高清 独家分发 单体作品 中出 颜射 女子校生 3P・4P 戏剧",
        "javtxt_release_date": "2020-07-20",
        "author_raw": "姫野ことめ",
        "video_category": "单体作品",
        "supplement_enrichment_status": "未补全",
        "ladder_tags": [],
        "ladder_tag_text": ""
      },
      {
        "actor_name": "姫野ことめ",
        "code": "OREC-553",
        "title": "ことめ",
        "author": "",
        "release_date": "2020-07-13",
        "avfan_url": "https://avfan.com/zh-CN/movies/NB1I4WgU",
        "page_number": 2,
        "javtxt_enrichment_status": "已补全",
        "javtxt_movie_id": "372762",
        "javtxt_url": "https://javtxt.top/v/372762",
        "javtxt_tags": "配信専用 素人 搭讪 美少女 童贞",
        "javtxt_release_date": "2020-07-13",
        "author_raw": "未公开",
        "video_category": "",
        "supplement_enrichment_status": "未补全",
        "ladder_tags": [],
        "ladder_tag_text": ""
      },
      {
        "actor_name": "姫野ことめ",
        "code": "NAMA-090",
        "title": "332NAMA-090",
        "author": "",
        "release_date": "2020-07-13",
        "avfan_url": "https://avfan.com/zh-CN/movies/38uAEchq",
        "page_number": 2,
        "javtxt_enrichment_status": "已补全",
        "javtxt_movie_id": "372765",
        "javtxt_url": "https://javtxt.top/v/372765",
        "javtxt_tags": "独家分发 配信専用 素人 第一人称 苗条 自慰器 美乳 美尻 中出 口内射精",
        "javtxt_release_date": "2020-07-13",
        "author_raw": "未公开",
        "video_category": "",
        "supplement_enrichment_status": "未补全",
        "ladder_tags": [],
        "ladder_tag_text": ""
      },
      {
        "actor_name": "姫野ことめ",
        "code": "APKH-147",
        "title": "【凄い腰ツキのペット娘】華奢美少女を飼って籠ってぬっぽり過激性交ハメ撮り",
        "author": "姫野ことめ",
        "release_date": "2020-07-12",
        "avfan_url": "https://avfan.com/zh-CN/movies/f54F5PiU",
        "page_number": 2,
        "javtxt_enrichment_status": "已补全",
        "javtxt_movie_id": "320429",
        "javtxt_url": "https://javtxt.top/v/320429",
        "javtxt_tags": "高清 独家分发 女子校生 单体作品 中出 苗条 第一人称 颜射",
        "javtxt_release_date": "2020-07-12",
        "author_raw": "姫野ことめ",
        "video_category": "单体作品",
        "supplement_enrichment_status": "未补全",
        "ladder_tags": [],
        "ladder_tag_text": ""
      },
      {
        "actor_name": "姫野ことめ",
        "code": "MKON-032",
        "title": "清纯可爱的图书委员女友怎么可能是隐藏的荡妇！姬野琴目",
        "author": "姫野ことめ",
        "release_date": "2020-07-05",
        "avfan_url": "https://avfan.com/zh-CN/movies/aJ2OdVTi",
        "page_number": 1,
        "javtxt_enrichment_status": "已补全",
        "javtxt_movie_id": "319978",
        "javtxt_url": "https://javtxt.top/v/319978",
        "javtxt_tags": "单体作品 妄想族 中出 3P・4P 学生服 女子校生 独家分发 高清 绿帽子・NTR",
        "javtxt_release_date": "2020-07-05",
        "author_raw": "姫野ことめ",
        "video_category": "单体作品",
        "supplement_enrichment_status": "未补全",
        "ladder_tags": [],
        "ladder_tag_text": ""
      },
      {
        "actor_name": "姫野ことめ",
        "code": "DAC-011",
        "title": "どっく あまちゅあ ちゃんねる",
        "author": "",
        "release_date": "2020-06-12",
        "avfan_url": "https://avfan.com/zh-CN/movies/v2TP70im",
        "page_number": 2,
        "javtxt_enrichment_status": "已补全",
        "javtxt_movie_id": "318334",
        "javtxt_url": "https://javtxt.top/v/318334",
        "javtxt_tags": "高清 第一人称 中出 素人",
        "javtxt_release_date": "2020-06-12",
        "author_raw": "未公开",
        "video_category": "",
        "supplement_enrichment_status": "未补全",
        "ladder_tags": [],
        "ladder_tag_text": ""
      },
      {
        "actor_name": "姫野ことめ",
        "code": "SVDVD-800",
        "title": "将电压调至86倍的超强震动棒塞入阴道，被牵着在街上强制高潮散步！",
        "author": "",
        "release_date": "2020-06-11",
        "avfan_url": "https://avfan.com/zh-CN/movies/xEFlfWQw",
        "page_number": 2,
        "javtxt_enrichment_status": "已补全",
        "javtxt_movie_id": "318297",
        "javtxt_url": "https://javtxt.top/v/318297",
        "javtxt_tags": "高清 浴室 野外・露出 跳蛋 搭讪 羞耻 トリプルHAPPY30％OFFセール第3弾",
        "javtxt_release_date": "2020-06-11",
        "author_raw": "未公开",
        "video_category": "共演作品",
        "supplement_enrichment_status": "未补全",
        "ladder_tags": [],
        "ladder_tag_text": ""
      },
      {
        "actor_name": "姫野ことめ",
        "code": "LAS-018",
        "title": "ことめちゃん",
        "author": "",
        "release_date": "2020-05-18",
        "avfan_url": "https://avfan.com/zh-CN/movies/TCmyXN2p",
        "page_number": 2,
        "javtxt_enrichment_status": "已补全",
        "javtxt_movie_id": "372302",
        "javtxt_url": "https://javtxt.top/v/372302",
        "javtxt_tags": "配信専用 素人 搭讪 童顔 オモチャ",
        "javtxt_release_date": "2020-05-18",
        "author_raw": "未公开",
        "video_category": "",
        "supplement_enrichment_status": "未补全",
        "ladder_tags": [],
        "ladder_tag_text": ""
      },
      {
        "actor_name": "姫野ことめ",
        "code": "BIG-063",
        "title": "ことみ",
        "author": "",
        "release_date": "2020-05-07",
        "avfan_url": "https://avfan.com/zh-CN/movies/cPTJgj3C",
        "page_number": 2,
        "javtxt_enrichment_status": "已补全",
        "javtxt_movie_id": "372206",
        "javtxt_url": "https://javtxt.top/v/372206",
        "javtxt_tags": "配信専用 素人 中出 鬼畜 制服 童顔 潮吹",
        "javtxt_release_date": "2020-05-07",
        "author_raw": "未公开",
        "video_category": "",
        "supplement_enrichment_status": "未补全",
        "ladder_tags": [],
        "ladder_tag_text": ""
      },
      {
        "actor_name": "姫野ことめ",
        "code": "BBAN-278",
        "title": "絶対服従 いいなりメイド レズビアン調教 ～奴●メイドの館～ 姫野ことめ",
        "author": "姫野ことめ 澤村レイコ",
        "release_date": "2020-05-02",
        "avfan_url": "https://avfan.com/zh-CN/movies/gX9faeTl",
        "page_number": 3,
        "javtxt_enrichment_status": "已补全",
        "javtxt_movie_id": "315868",
        "javtxt_url": "https://javtxt.top/v/315868",
        "javtxt_tags": "高清 独家分发 美少女 女同 女仆 同性接吻",
        "javtxt_release_date": "2020-05-02",
        "author_raw": "姫野ことめ 澤村レイコ",
        "video_category": "共演作品",
        "supplement_enrichment_status": "未补全",
        "ladder_tags": [
          "仙徐娘",
          "绾青瀑",
          "楚腰轻",
          "凝霜雪"
        ],
        "ladder_tag_text": "仙徐娘 | 绾青瀑 | 楚腰轻 | 凝霜雪"
      },
      {
        "actor_name": "姫野ことめ",
        "code": "MFC-003",
        "title": "ことめ",
        "author": "",
        "release_date": "2020-04-22",
        "avfan_url": "https://avfan.com/zh-CN/movies/nybgvwHD",
        "page_number": 3,
        "javtxt_enrichment_status": "已补全",
        "javtxt_movie_id": "372052",
        "javtxt_url": "https://javtxt.top/v/372052",
        "javtxt_tags": "按摩棒 オモチャ 自慰器 童顔 清楚 女大学生 第一人称 素人 配信専用",
        "javtxt_release_date": "2020-04-22",
        "author_raw": "未公开",
        "video_category": "",
        "supplement_enrichment_status": "未补全",
        "ladder_tags": [],
        "ladder_tag_text": ""
      },
      {
        "actor_name": "姫野ことめ",
        "code": "SIRO-4115",
        "title": "首次拍摄 - 无法控制高潮的少女 - 19岁女大学生。一位以读书为爱好的认真19岁少女登场。她说着'从没和这么年长的人...'。※由于女孩反应强烈，建议使用耳机观看。素人应募，首次成人影片拍摄",
        "author": "",
        "release_date": "2020-04-14",
        "avfan_url": "https://avfan.com/zh-CN/movies/NDtOWgUj",
        "page_number": 3,
        "javtxt_enrichment_status": "已补全",
        "javtxt_movie_id": "371970",
        "javtxt_url": "https://javtxt.top/v/371970",
        "javtxt_tags": "独家分发 配信専用 素人 初撮り 第一人称 女大学生 苗条 美尻 颜射",
        "javtxt_release_date": "2020-04-14",
        "author_raw": "未公开",
        "video_category": "",
        "supplement_enrichment_status": "未补全",
        "ladder_tags": [],
        "ladder_tag_text": ""
      },
      {
        "actor_name": "姫野ことめ",
        "code": "ATID-409",
        "title": "恥辱の教育実習生17",
        "author": "姫野ことめ",
        "release_date": "2020-04-04",
        "avfan_url": "https://avfan.com/zh-CN/movies/dWrCXkDF",
        "page_number": 3,
        "javtxt_enrichment_status": "已补全",
        "javtxt_movie_id": "313951",
        "javtxt_url": "https://javtxt.top/v/313951",
        "javtxt_tags": "独家分发 高清 耻辱 女教师 女大学生 单体作品",
        "javtxt_release_date": "2020-04-04",
        "author_raw": "姫野ことめ",
        "video_category": "单体作品",
        "supplement_enrichment_status": "未补全",
        "ladder_tags": [],
        "ladder_tag_text": ""
      },
      {
        "actor_name": "姫野ことめ",
        "code": "ADN-237",
        "title": "大学受験の当日、私はハゲオヤジに犯●れました…。",
        "author": "",
        "release_date": "2020-02-01",
        "avfan_url": "https://avfan.com/zh-CN/movies/pAg7N6Jw",
        "page_number": 3,
        "javtxt_enrichment_status": "无搜索结果",
        "javtxt_movie_id": "",
        "javtxt_url": "",
        "javtxt_tags": "",
        "javtxt_release_date": "",
        "author_raw": "",
        "video_category": "共演作品",
        "supplement_enrichment_status": "未补全",
        "ladder_tags": [],
        "ladder_tag_text": ""
      }
    ],
    "collaborator_sections": [],
    "raw_web_movie_count": 98
  },
  "refreshed_at": "2026-07-08 09:09:05",
  "refresh_duration_ms": 893,
  "refresh_duration_text": "1秒"
}