{
  "actor": {
    "name": "徳島理子",
    "birthday": "1982/11/30",
    "age": "43",
    "matched": true,
    "actor_id": "r4DpLv1S",
    "binghuo_person_id": "4113",
    "binghuo_height": "156",
    "binghuo_bust": "101",
    "binghuo_cup": "H",
    "binghuo_waist": "69",
    "binghuo_hip": "96",
    "baomu_birthday": "",
    "baomu_height": "156",
    "baomu_bust": "101",
    "baomu_cup": "H",
    "baomu_waist": "69",
    "baomu_hip": "96",
    "baomu_enrichment_status": "已补全",
    "web_url": "https://avfan.com/casts/r4DpLv1S",
    "ladder_tier": "",
    "update_status": "active",
    "local_video_count": 1,
    "appearance_code_count": 15,
    "code_prefix_library_count": 7,
    "local_prefix_distribution": [
      {
        "prefix": "HBAD",
        "video_count": 1
      }
    ],
    "local_year_distribution": [
      {
        "year": "2018",
        "video_count": 1
      }
    ],
    "web_enrichment_status": "天限阁: 已补全 | 辛聚谷: 已补全 | 并火: 已补全 | 保木: 已补全",
    "web_total_pages": 1,
    "web_total_videos": 38,
    "eligible_video_count": 14,
    "eligible_enriched_video_count": 14,
    "web_update_frequency": {
      "video_count": 14,
      "month_count": 68,
      "videos_per_month": 0.20588235294117646
    },
    "web_last_enriched_at": "2026-06-30 02:34:03",
    "web_earliest_release_date": "2020-08-02",
    "web_latest_release_date": "2026-03-04",
    "web_prefix_distribution": [
      {
        "prefix": "ALDN",
        "video_count": 1
      },
      {
        "prefix": "ANB",
        "video_count": 1
      },
      {
        "prefix": "CADV",
        "video_count": 1
      },
      {
        "prefix": "CMC",
        "video_count": 1
      },
      {
        "prefix": "FJIN",
        "video_count": 1
      },
      {
        "prefix": "GMEM",
        "video_count": 1
      },
      {
        "prefix": "GMJK",
        "video_count": 1
      },
      {
        "prefix": "GVH",
        "video_count": 1
      },
      {
        "prefix": "ITSR",
        "video_count": 1
      },
      {
        "prefix": "JUAN",
        "video_count": 1
      },
      {
        "prefix": "MADM",
        "video_count": 1
      },
      {
        "prefix": "OPUD",
        "video_count": 1
      },
      {
        "prefix": "RNA",
        "video_count": 1
      },
      {
        "prefix": "YOCH",
        "video_count": 1
      }
    ],
    "web_year_distribution": [
      {
        "year": "2026",
        "video_count": 1
      },
      {
        "year": "2025",
        "video_count": 5
      },
      {
        "year": "2024",
        "video_count": 2
      },
      {
        "year": "2023",
        "video_count": 1
      },
      {
        "year": "2021",
        "video_count": 3
      },
      {
        "year": "2020",
        "video_count": 2
      }
    ],
    "web_video_category_distribution": [
      {
        "name": "单体作品",
        "video_count": 10
      },
      {
        "name": "共演作品",
        "video_count": 2
      },
      {
        "name": "暂无分类信息",
        "video_count": 2
      }
    ],
    "local_videos": [
      {
        "code": "HBAD-452",
        "title": "息子の友達のマセガキ共に甘えたふりをされて犯●れ、有り余る若い男達の性処理をさせられる柔らかい母親の肉穴",
        "author": "徳島理子",
        "duration": "2:00:52",
        "size": "0.794",
        "storage_location": "机械硬盘",
        "avfan_movie_id": "IGYSHTCt",
        "javtxt_movie_id": "",
        "javtxt_url": "",
        "javtxt_title": "",
        "javtxt_actors": "",
        "javtxt_tags": "",
        "video_category": "",
        "release_date": "2018-11-22",
        "maker": "Hibino",
        "publisher": "BABE",
        "avfan_enrichment_status": "未补全",
        "javtxt_enrichment_status": "未补全",
        "enrichment_status": "天限阁: 未补全 | 辛聚谷: 未补全",
        "ladder_tags": [],
        "ladder_tag_text": ""
      }
    ],
    "web_movies": [
      {
        "actor_name": "徳島理子",
        "code": "YOCH-029",
        "title": "私人調●ヤリ部屋団地近隣に住む男に常に物色されていた人妻に起きた悲劇の肉感強●羽交い締めからのチ●ポ狂い",
        "author": "徳島理子",
        "release_date": "2026-03-04",
        "avfan_url": "https://avfan.com/zh-CN/movies/rv2Z5Lv1",
        "page_number": 1,
        "javtxt_enrichment_status": "已补全",
        "javtxt_movie_id": "537118",
        "javtxt_url": "https://javtxt.top/v/537118",
        "javtxt_tags": "熟女 人妻・主妇 耻辱 鬼畜 中出 高清 单体作品 4K",
        "javtxt_release_date": "2026-03-04",
        "author_raw": "徳島理子",
        "video_category": "单体作品",
        "supplement_enrichment_status": "未补全",
        "ladder_tags": [],
        "ladder_tag_text": ""
      },
      {
        "actor_name": "徳島理子",
        "code": "GMEM-141",
        "title": "鬼畜沼 極大チクビ豊満マゾ妻の性脳を覚醒させ、アナル＆マ○コ＆顔面を崩壊コア調教",
        "author": "徳島理子",
        "release_date": "2025-12-05",
        "avfan_url": "https://avfan.com/zh-CN/movies/C6WQWBbd",
        "page_number": 1,
        "javtxt_enrichment_status": "已补全",
        "javtxt_movie_id": "528415",
        "javtxt_url": "https://javtxt.top/v/528415",
        "javtxt_tags": "深喉 菊花 女色情狂 M女 灌肠 单体作品 独家分发 4K 高清",
        "javtxt_release_date": "2025-12-05",
        "author_raw": "徳島理子",
        "video_category": "单体作品",
        "supplement_enrichment_status": "未补全",
        "ladder_tags": [],
        "ladder_tag_text": ""
      },
      {
        "actor_name": "徳島理子",
        "code": "RNA-005",
        "title": "素人の縛り生中出し 【全身敏感熟女編】 面接にきた奥さんが巨乳だったのでさらって自宅に連れ込み2人がかりで無茶してみた…。",
        "author": "徳島理子",
        "release_date": "2025-08-01",
        "avfan_url": "https://avfan.com/zh-CN/movies/7EH4Zgaf",
        "page_number": 1,
        "javtxt_enrichment_status": "已补全",
        "javtxt_movie_id": "515693",
        "javtxt_url": "https://javtxt.top/v/515693",
        "javtxt_tags": "巨乳 束缚 中出 人妻・主妇 熟女 单体作品 高清",
        "javtxt_release_date": "2025-08-01",
        "author_raw": "徳島理子",
        "video_category": "单体作品",
        "supplement_enrichment_status": "未补全",
        "ladder_tags": [],
        "ladder_tag_text": ""
      },
      {
        "actor_name": "徳島理子",
        "code": "GMJK-025",
        "title": "場末スナックママ パトロン親父との言いなり凌●アナル破壊",
        "author": "徳島理子",
        "release_date": "2025-07-27",
        "avfan_url": "https://avfan.com/zh-CN/movies/Ie5BtHTC",
        "page_number": 1,
        "javtxt_enrichment_status": "已补全",
        "javtxt_movie_id": "515234",
        "javtxt_url": "https://javtxt.top/v/515234",
        "javtxt_tags": "熟女 肉感 肛交 菊花 巨乳 单体作品 高清",
        "javtxt_release_date": "2025-07-27",
        "author_raw": "徳島理子",
        "video_category": "单体作品",
        "supplement_enrichment_status": "未补全",
        "ladder_tags": [],
        "ladder_tag_text": ""
      },
      {
        "actor_name": "徳島理子",
        "code": "FJIN-083",
        "title": "W人妻拉致マチオ チ○ポの虜になるまでむちむち熟女を徹底的に中出し交遊を繰り返し痙攣イキを何度もさせたところ…佐久間楓",
        "author": "佐久間楓 徳島理子",
        "release_date": "2025-06-28",
        "avfan_url": "https://avfan.com/zh-CN/movies/H3QS47nr",
        "page_number": 1,
        "javtxt_enrichment_status": "已补全",
        "javtxt_movie_id": "512218",
        "javtxt_url": "https://javtxt.top/v/512218",
        "javtxt_tags": "深喉 人妻・主妇 鬼畜 3P・4P 妄想族 耻辱 独家分发 高清",
        "javtxt_release_date": "2025-06-28",
        "author_raw": "佐久間楓 徳島理子",
        "video_category": "共演作品",
        "supplement_enrichment_status": "未补全",
        "ladder_tags": [],
        "ladder_tag_text": ""
      },
      {
        "actor_name": "徳島理子",
        "code": "JUAN-023",
        "title": "变态姐姐和好色伯父还有正经堂兄一起享受双穴的快感",
        "author": "徳島理子",
        "release_date": "2025-03-01",
        "avfan_url": "https://avfan.com/zh-CN/movies/KZuQ389z",
        "page_number": 1,
        "javtxt_enrichment_status": "已补全",
        "javtxt_movie_id": "500182",
        "javtxt_url": "https://javtxt.top/v/500182",
        "javtxt_tags": "独家分发 巨乳 3P・4P 单体作品 中出 菊花 熟女 高清",
        "javtxt_release_date": "2025-03-01",
        "author_raw": "徳島理子",
        "video_category": "单体作品",
        "supplement_enrichment_status": "未补全",
        "ladder_tags": [],
        "ladder_tag_text": ""
      },
      {
        "actor_name": "徳島理子",
        "code": "ITSR-12602",
        "title": "「ああっ！ほぐれてるっ！奥までほぐれてるぅ！」奥様が中出しSEXで牝イキデトックス！！徳島さん（40歳）",
        "author": "徳島理子",
        "release_date": "2024-03-23",
        "avfan_url": "https://avfan.com/zh-CN/movies/Q9KyJpnJ",
        "page_number": 1,
        "javtxt_enrichment_status": "已补全",
        "javtxt_movie_id": "467181",
        "javtxt_url": "https://javtxt.top/v/467181",
        "javtxt_tags": "熟女 按摩 巨乳 中出 单体作品 高清",
        "javtxt_release_date": "2024-03-23",
        "author_raw": "徳島理子",
        "video_category": "单体作品",
        "supplement_enrichment_status": "未补全",
        "ladder_tags": [],
        "ladder_tag_text": ""
      },
      {
        "actor_name": "徳島理子",
        "code": "ALDN-281",
        "title": "岳母大人，您比我老婆好多了...",
        "author": "徳島理子",
        "release_date": "2024-02-24",
        "avfan_url": "https://avfan.com/zh-CN/movies/qv1WS1A5",
        "page_number": 1,
        "javtxt_enrichment_status": "已补全",
        "javtxt_movie_id": "464523",
        "javtxt_url": "https://javtxt.top/v/464523",
        "javtxt_tags": "高清 4K 独家分发 熟女 人妻・主妇 单体作品 中出 近亲相奸 巨乳",
        "javtxt_release_date": "2024-02-24",
        "author_raw": "徳島理子",
        "video_category": "单体作品",
        "supplement_enrichment_status": "未补全",
        "ladder_tags": [
          "熟女"
        ],
        "ladder_tag_text": "熟女"
      },
      {
        "actor_name": "徳島理子",
        "code": "CADV-888",
        "title": "淫乱美女高潮痴态性爱20人8小时",
        "author": "",
        "release_date": "2023-11-28",
        "avfan_url": "https://avfan.com/zh-CN/movies/byYHl1O7",
        "page_number": 1,
        "javtxt_enrichment_status": "无搜索结果",
        "javtxt_movie_id": "",
        "javtxt_url": "",
        "javtxt_tags": "",
        "javtxt_release_date": "",
        "author_raw": "",
        "video_category": "",
        "supplement_enrichment_status": "未补全",
        "ladder_tags": [],
        "ladder_tag_text": ""
      },
      {
        "actor_name": "徳島理子",
        "code": "CMC-258",
        "title": "爆乳肉尻未亡人 スティング洗脳事件簿",
        "author": "徳島理子",
        "release_date": "2021-07-15",
        "avfan_url": "https://avfan.com/zh-CN/movies/Ztgn1JcL",
        "page_number": 1,
        "javtxt_enrichment_status": "已补全",
        "javtxt_movie_id": "379388",
        "javtxt_url": "https://javtxt.top/v/379388",
        "javtxt_tags": "高清 独家分发 巨臀 单体作品 灌肠 巨乳 SM",
        "javtxt_release_date": "2021-07-15",
        "author_raw": "徳島理子",
        "video_category": "单体作品",
        "supplement_enrichment_status": "未补全",
        "ladder_tags": [],
        "ladder_tag_text": ""
      },
      {
        "actor_name": "徳島理子",
        "code": "MADM-139",
        "title": "エロ年増",
        "author": "羽田希 真田紗也子 徳島理子 森ほたる",
        "release_date": "2021-03-22",
        "avfan_url": "https://avfan.com/zh-CN/movies/KZIWZ89z",
        "page_number": 1,
        "javtxt_enrichment_status": "已补全",
        "javtxt_movie_id": "338759",
        "javtxt_url": "https://javtxt.top/v/338759",
        "javtxt_tags": "中出 玩具 乳交 熟女 人妻・主妇 独家分发 高清",
        "javtxt_release_date": "2021-03-22",
        "author_raw": "羽田希 真田紗也子 徳島理子 森ほたる",
        "video_category": "",
        "supplement_enrichment_status": "未补全",
        "ladder_tags": [],
        "ladder_tag_text": ""
      },
      {
        "actor_name": "徳島理子",
        "code": "GVH-198",
        "title": "姑の卑猥過ぎる巨乳を狙う娘婿",
        "author": "",
        "release_date": "2021-02-17",
        "avfan_url": "https://avfan.com/zh-CN/movies/Aii48zU0",
        "page_number": 1,
        "javtxt_enrichment_status": "无搜索结果",
        "javtxt_movie_id": "",
        "javtxt_url": "",
        "javtxt_tags": "",
        "javtxt_release_date": "",
        "author_raw": "",
        "video_category": "共演作品",
        "supplement_enrichment_status": "未补全",
        "ladder_tags": [],
        "ladder_tag_text": ""
      },
      {
        "actor_name": "徳島理子",
        "code": "OPUD-329",
        "title": "ソープに堕ちたG-cup爆乳妻 食糞アナル中出し調教",
        "author": "徳島理子",
        "release_date": "2020-12-20",
        "avfan_url": "https://avfan.com/zh-CN/movies/I3gFTHTC",
        "page_number": 1,
        "javtxt_enrichment_status": "已补全",
        "javtxt_movie_id": "332683",
        "javtxt_url": "https://javtxt.top/v/332683",
        "javtxt_tags": "高清 独家分发 单体作品 排泄物 耻辱 巨乳 食粪 风俗娘",
        "javtxt_release_date": "2020-12-20",
        "author_raw": "徳島理子",
        "video_category": "单体作品",
        "supplement_enrichment_status": "未补全",
        "ladder_tags": [],
        "ladder_tag_text": ""
      },
      {
        "actor_name": "徳島理子",
        "code": "ANB-177",
        "title": "綺麗でいやらしい叔母さんの爆乳で豊満な肉体に埋もれる僕",
        "author": "徳島理子",
        "release_date": "2020-08-02",
        "avfan_url": "https://avfan.com/zh-CN/movies/CV9lUBbd",
        "page_number": 1,
        "javtxt_enrichment_status": "已补全",
        "javtxt_movie_id": "321725",
        "javtxt_url": "https://javtxt.top/v/321725",
        "javtxt_tags": "熟女 巨乳 乳交 颜射 人妻・主妇 数位马赛克 单体作品 独家分发 高清",
        "javtxt_release_date": "2020-08-02",
        "author_raw": "徳島理子",
        "video_category": "单体作品",
        "supplement_enrichment_status": "未补全",
        "ladder_tags": [],
        "ladder_tag_text": ""
      }
    ],
    "eligible_web_movies": [
      {
        "actor_name": "徳島理子",
        "code": "YOCH-029",
        "title": "私人調●ヤリ部屋団地近隣に住む男に常に物色されていた人妻に起きた悲劇の肉感強●羽交い締めからのチ●ポ狂い",
        "author": "徳島理子",
        "release_date": "2026-03-04",
        "avfan_url": "https://avfan.com/zh-CN/movies/rv2Z5Lv1",
        "page_number": 1,
        "javtxt_enrichment_status": "已补全",
        "javtxt_movie_id": "537118",
        "javtxt_url": "https://javtxt.top/v/537118",
        "javtxt_tags": "熟女 人妻・主妇 耻辱 鬼畜 中出 高清 单体作品 4K",
        "javtxt_release_date": "2026-03-04",
        "author_raw": "徳島理子",
        "video_category": "单体作品",
        "supplement_enrichment_status": "未补全",
        "ladder_tags": [],
        "ladder_tag_text": ""
      },
      {
        "actor_name": "徳島理子",
        "code": "GMEM-141",
        "title": "鬼畜沼 極大チクビ豊満マゾ妻の性脳を覚醒させ、アナル＆マ○コ＆顔面を崩壊コア調教",
        "author": "徳島理子",
        "release_date": "2025-12-05",
        "avfan_url": "https://avfan.com/zh-CN/movies/C6WQWBbd",
        "page_number": 1,
        "javtxt_enrichment_status": "已补全",
        "javtxt_movie_id": "528415",
        "javtxt_url": "https://javtxt.top/v/528415",
        "javtxt_tags": "深喉 菊花 女色情狂 M女 灌肠 单体作品 独家分发 4K 高清",
        "javtxt_release_date": "2025-12-05",
        "author_raw": "徳島理子",
        "video_category": "单体作品",
        "supplement_enrichment_status": "未补全",
        "ladder_tags": [],
        "ladder_tag_text": ""
      },
      {
        "actor_name": "徳島理子",
        "code": "RNA-005",
        "title": "素人の縛り生中出し 【全身敏感熟女編】 面接にきた奥さんが巨乳だったのでさらって自宅に連れ込み2人がかりで無茶してみた…。",
        "author": "徳島理子",
        "release_date": "2025-08-01",
        "avfan_url": "https://avfan.com/zh-CN/movies/7EH4Zgaf",
        "page_number": 1,
        "javtxt_enrichment_status": "已补全",
        "javtxt_movie_id": "515693",
        "javtxt_url": "https://javtxt.top/v/515693",
        "javtxt_tags": "巨乳 束缚 中出 人妻・主妇 熟女 单体作品 高清",
        "javtxt_release_date": "2025-08-01",
        "author_raw": "徳島理子",
        "video_category": "单体作品",
        "supplement_enrichment_status": "未补全",
        "ladder_tags": [],
        "ladder_tag_text": ""
      },
      {
        "actor_name": "徳島理子",
        "code": "GMJK-025",
        "title": "場末スナックママ パトロン親父との言いなり凌●アナル破壊",
        "author": "徳島理子",
        "release_date": "2025-07-27",
        "avfan_url": "https://avfan.com/zh-CN/movies/Ie5BtHTC",
        "page_number": 1,
        "javtxt_enrichment_status": "已补全",
        "javtxt_movie_id": "515234",
        "javtxt_url": "https://javtxt.top/v/515234",
        "javtxt_tags": "熟女 肉感 肛交 菊花 巨乳 单体作品 高清",
        "javtxt_release_date": "2025-07-27",
        "author_raw": "徳島理子",
        "video_category": "单体作品",
        "supplement_enrichment_status": "未补全",
        "ladder_tags": [],
        "ladder_tag_text": ""
      },
      {
        "actor_name": "徳島理子",
        "code": "FJIN-083",
        "title": "W人妻拉致マチオ チ○ポの虜になるまでむちむち熟女を徹底的に中出し交遊を繰り返し痙攣イキを何度もさせたところ…佐久間楓",
        "author": "佐久間楓 徳島理子",
        "release_date": "2025-06-28",
        "avfan_url": "https://avfan.com/zh-CN/movies/H3QS47nr",
        "page_number": 1,
        "javtxt_enrichment_status": "已补全",
        "javtxt_movie_id": "512218",
        "javtxt_url": "https://javtxt.top/v/512218",
        "javtxt_tags": "深喉 人妻・主妇 鬼畜 3P・4P 妄想族 耻辱 独家分发 高清",
        "javtxt_release_date": "2025-06-28",
        "author_raw": "佐久間楓 徳島理子",
        "video_category": "共演作品",
        "supplement_enrichment_status": "未补全",
        "ladder_tags": [],
        "ladder_tag_text": ""
      },
      {
        "actor_name": "徳島理子",
        "code": "JUAN-023",
        "title": "变态姐姐和好色伯父还有正经堂兄一起享受双穴的快感",
        "author": "徳島理子",
        "release_date": "2025-03-01",
        "avfan_url": "https://avfan.com/zh-CN/movies/KZuQ389z",
        "page_number": 1,
        "javtxt_enrichment_status": "已补全",
        "javtxt_movie_id": "500182",
        "javtxt_url": "https://javtxt.top/v/500182",
        "javtxt_tags": "独家分发 巨乳 3P・4P 单体作品 中出 菊花 熟女 高清",
        "javtxt_release_date": "2025-03-01",
        "author_raw": "徳島理子",
        "video_category": "单体作品",
        "supplement_enrichment_status": "未补全",
        "ladder_tags": [],
        "ladder_tag_text": ""
      },
      {
        "actor_name": "徳島理子",
        "code": "ITSR-12602",
        "title": "「ああっ！ほぐれてるっ！奥までほぐれてるぅ！」奥様が中出しSEXで牝イキデトックス！！徳島さん（40歳）",
        "author": "徳島理子",
        "release_date": "2024-03-23",
        "avfan_url": "https://avfan.com/zh-CN/movies/Q9KyJpnJ",
        "page_number": 1,
        "javtxt_enrichment_status": "已补全",
        "javtxt_movie_id": "467181",
        "javtxt_url": "https://javtxt.top/v/467181",
        "javtxt_tags": "熟女 按摩 巨乳 中出 单体作品 高清",
        "javtxt_release_date": "2024-03-23",
        "author_raw": "徳島理子",
        "video_category": "单体作品",
        "supplement_enrichment_status": "未补全",
        "ladder_tags": [],
        "ladder_tag_text": ""
      },
      {
        "actor_name": "徳島理子",
        "code": "ALDN-281",
        "title": "岳母大人，您比我老婆好多了...",
        "author": "徳島理子",
        "release_date": "2024-02-24",
        "avfan_url": "https://avfan.com/zh-CN/movies/qv1WS1A5",
        "page_number": 1,
        "javtxt_enrichment_status": "已补全",
        "javtxt_movie_id": "464523",
        "javtxt_url": "https://javtxt.top/v/464523",
        "javtxt_tags": "高清 4K 独家分发 熟女 人妻・主妇 单体作品 中出 近亲相奸 巨乳",
        "javtxt_release_date": "2024-02-24",
        "author_raw": "徳島理子",
        "video_category": "单体作品",
        "supplement_enrichment_status": "未补全",
        "ladder_tags": [
          "熟女"
        ],
        "ladder_tag_text": "熟女"
      },
      {
        "actor_name": "徳島理子",
        "code": "CADV-888",
        "title": "淫乱美女高潮痴态性爱20人8小时",
        "author": "",
        "release_date": "2023-11-28",
        "avfan_url": "https://avfan.com/zh-CN/movies/byYHl1O7",
        "page_number": 1,
        "javtxt_enrichment_status": "无搜索结果",
        "javtxt_movie_id": "",
        "javtxt_url": "",
        "javtxt_tags": "",
        "javtxt_release_date": "",
        "author_raw": "",
        "video_category": "",
        "supplement_enrichment_status": "未补全",
        "ladder_tags": [],
        "ladder_tag_text": ""
      },
      {
        "actor_name": "徳島理子",
        "code": "CMC-258",
        "title": "爆乳肉尻未亡人 スティング洗脳事件簿",
        "author": "徳島理子",
        "release_date": "2021-07-15",
        "avfan_url": "https://avfan.com/zh-CN/movies/Ztgn1JcL",
        "page_number": 1,
        "javtxt_enrichment_status": "已补全",
        "javtxt_movie_id": "379388",
        "javtxt_url": "https://javtxt.top/v/379388",
        "javtxt_tags": "高清 独家分发 巨臀 单体作品 灌肠 巨乳 SM",
        "javtxt_release_date": "2021-07-15",
        "author_raw": "徳島理子",
        "video_category": "单体作品",
        "supplement_enrichment_status": "未补全",
        "ladder_tags": [],
        "ladder_tag_text": ""
      },
      {
        "actor_name": "徳島理子",
        "code": "MADM-139",
        "title": "エロ年増",
        "author": "羽田希 真田紗也子 徳島理子 森ほたる",
        "release_date": "2021-03-22",
        "avfan_url": "https://avfan.com/zh-CN/movies/KZIWZ89z",
        "page_number": 1,
        "javtxt_enrichment_status": "已补全",
        "javtxt_movie_id": "338759",
        "javtxt_url": "https://javtxt.top/v/338759",
        "javtxt_tags": "中出 玩具 乳交 熟女 人妻・主妇 独家分发 高清",
        "javtxt_release_date": "2021-03-22",
        "author_raw": "羽田希 真田紗也子 徳島理子 森ほたる",
        "video_category": "",
        "supplement_enrichment_status": "未补全",
        "ladder_tags": [],
        "ladder_tag_text": ""
      },
      {
        "actor_name": "徳島理子",
        "code": "GVH-198",
        "title": "姑の卑猥過ぎる巨乳を狙う娘婿",
        "author": "",
        "release_date": "2021-02-17",
        "avfan_url": "https://avfan.com/zh-CN/movies/Aii48zU0",
        "page_number": 1,
        "javtxt_enrichment_status": "无搜索结果",
        "javtxt_movie_id": "",
        "javtxt_url": "",
        "javtxt_tags": "",
        "javtxt_release_date": "",
        "author_raw": "",
        "video_category": "共演作品",
        "supplement_enrichment_status": "未补全",
        "ladder_tags": [],
        "ladder_tag_text": ""
      },
      {
        "actor_name": "徳島理子",
        "code": "OPUD-329",
        "title": "ソープに堕ちたG-cup爆乳妻 食糞アナル中出し調教",
        "author": "徳島理子",
        "release_date": "2020-12-20",
        "avfan_url": "https://avfan.com/zh-CN/movies/I3gFTHTC",
        "page_number": 1,
        "javtxt_enrichment_status": "已补全",
        "javtxt_movie_id": "332683",
        "javtxt_url": "https://javtxt.top/v/332683",
        "javtxt_tags": "高清 独家分发 单体作品 排泄物 耻辱 巨乳 食粪 风俗娘",
        "javtxt_release_date": "2020-12-20",
        "author_raw": "徳島理子",
        "video_category": "单体作品",
        "supplement_enrichment_status": "未补全",
        "ladder_tags": [],
        "ladder_tag_text": ""
      },
      {
        "actor_name": "徳島理子",
        "code": "ANB-177",
        "title": "綺麗でいやらしい叔母さんの爆乳で豊満な肉体に埋もれる僕",
        "author": "徳島理子",
        "release_date": "2020-08-02",
        "avfan_url": "https://avfan.com/zh-CN/movies/CV9lUBbd",
        "page_number": 1,
        "javtxt_enrichment_status": "已补全",
        "javtxt_movie_id": "321725",
        "javtxt_url": "https://javtxt.top/v/321725",
        "javtxt_tags": "熟女 巨乳 乳交 颜射 人妻・主妇 数位马赛克 单体作品 独家分发 高清",
        "javtxt_release_date": "2020-08-02",
        "author_raw": "徳島理子",
        "video_category": "单体作品",
        "supplement_enrichment_status": "未补全",
        "ladder_tags": [],
        "ladder_tag_text": ""
      }
    ],
    "collaborator_sections": [],
    "raw_web_movie_count": 38
  },
  "refreshed_at": "2026-07-08 09:11:59",
  "refresh_duration_ms": 326,
  "refresh_duration_text": "0秒"
}