{
  "actor": {
    "name": "木葉ちひろ",
    "birthday": "1997/10/6",
    "age": "28",
    "matched": false,
    "actor_id": "asbOdVTi",
    "binghuo_person_id": "3734",
    "binghuo_height": "172",
    "binghuo_bust": "86",
    "binghuo_cup": "E",
    "binghuo_waist": "59",
    "binghuo_hip": "85",
    "baomu_birthday": "1997-10-05",
    "baomu_height": "172",
    "baomu_bust": "86",
    "baomu_cup": "E",
    "baomu_waist": "59",
    "baomu_hip": "85",
    "baomu_enrichment_status": "已补全",
    "web_url": "https://avfan.com/casts/asbOdVTi",
    "ladder_tier": "",
    "update_status": "inactive",
    "local_video_count": 0,
    "appearance_code_count": 11,
    "code_prefix_library_count": 1,
    "local_prefix_distribution": [],
    "local_year_distribution": [],
    "web_enrichment_status": "天限阁: 已补全 | 辛聚谷: 已补全 | 并火: 已补全 | 保木: 已补全",
    "web_total_pages": 3,
    "web_total_videos": 64,
    "eligible_video_count": 19,
    "eligible_enriched_video_count": 19,
    "web_update_frequency": {
      "video_count": 19,
      "month_count": 51,
      "videos_per_month": 0.37254901960784315
    },
    "web_last_enriched_at": "2026-06-30 02:34:04",
    "web_earliest_release_date": "2020-03-10",
    "web_latest_release_date": "2024-05-24",
    "web_prefix_distribution": [
      {
        "prefix": "N",
        "video_count": 6
      },
      {
        "prefix": "BANK",
        "video_count": 3
      },
      {
        "prefix": "BTGL",
        "video_count": 2
      },
      {
        "prefix": "BANS",
        "video_count": 1
      },
      {
        "prefix": "BSKC",
        "video_count": 1
      },
      {
        "prefix": "ELLO",
        "video_count": 1
      },
      {
        "prefix": "ERHV",
        "video_count": 1
      },
      {
        "prefix": "HEYZO",
        "video_count": 1
      },
      {
        "prefix": "HNHU",
        "video_count": 1
      },
      {
        "prefix": "JUL",
        "video_count": 1
      },
      {
        "prefix": "PCR",
        "video_count": 1
      }
    ],
    "web_year_distribution": [
      {
        "year": "2024",
        "video_count": 1
      },
      {
        "year": "2023",
        "video_count": 3
      },
      {
        "year": "2022",
        "video_count": 1
      },
      {
        "year": "2021",
        "video_count": 8
      },
      {
        "year": "2020",
        "video_count": 6
      }
    ],
    "web_video_category_distribution": [
      {
        "name": "单体作品",
        "video_count": 2
      },
      {
        "name": "共演作品",
        "video_count": 2
      },
      {
        "name": "暂无分类信息",
        "video_count": 15
      }
    ],
    "local_videos": [],
    "web_movies": [
      {
        "actor_name": "木葉ちひろ",
        "code": "PCR-134",
        "title": "知り合いの娘と二人っきりに…",
        "author": "",
        "release_date": "2024-05-24",
        "avfan_url": "https://avfan.com/zh-CN/movies/Om22K5H0",
        "page_number": 1,
        "javtxt_enrichment_status": "无搜索结果",
        "javtxt_movie_id": "",
        "javtxt_url": "",
        "javtxt_tags": "",
        "javtxt_release_date": "",
        "author_raw": "",
        "video_category": "",
        "supplement_enrichment_status": "未补全",
        "ladder_tags": [],
        "ladder_tag_text": ""
      },
      {
        "actor_name": "木葉ちひろ",
        "code": "BSKC-032",
        "title": "歯科衛生士/社会人",
        "author": "",
        "release_date": "2023-09-29",
        "avfan_url": "https://avfan.com/zh-CN/movies/ZtGc6JcL",
        "page_number": 1,
        "javtxt_enrichment_status": "无搜索结果",
        "javtxt_movie_id": "",
        "javtxt_url": "",
        "javtxt_tags": "",
        "javtxt_release_date": "",
        "author_raw": "",
        "video_category": "",
        "supplement_enrichment_status": "未补全",
        "ladder_tags": [],
        "ladder_tag_text": ""
      },
      {
        "actor_name": "木葉ちひろ",
        "code": "ERHV-008",
        "title": "西○布高級ラウンジ嬢R 太パパとのプライベートハメ撮り映像流出",
        "author": "",
        "release_date": "2023-06-27",
        "avfan_url": "https://avfan.com/zh-CN/movies/v2wtn0im",
        "page_number": 1,
        "javtxt_enrichment_status": "已补全",
        "javtxt_movie_id": "441827",
        "javtxt_url": "https://javtxt.top/v/441827",
        "javtxt_tags": "高清 口交 中出 第一人称 苗条",
        "javtxt_release_date": "2023-06-27",
        "author_raw": "未公开",
        "video_category": "",
        "supplement_enrichment_status": "未补全",
        "ladder_tags": [],
        "ladder_tag_text": ""
      },
      {
        "actor_name": "木葉ちひろ",
        "code": "HNHU-053",
        "title": "個撮ナンパ ＃天使級美女 ＃アニ声オナニー ＃ なま中出し ＃ ねっとり系ジュボフェラ ＃",
        "author": "",
        "release_date": "2023-04-02",
        "avfan_url": "https://avfan.com/zh-CN/movies/dWK9pkDF",
        "page_number": 1,
        "javtxt_enrichment_status": "已补全",
        "javtxt_movie_id": "434250",
        "javtxt_url": "https://javtxt.top/v/434250",
        "javtxt_tags": "素人 搭讪 手淫 中出 美乳 口交 高清",
        "javtxt_release_date": "2023-04-02",
        "author_raw": "未公开",
        "video_category": "",
        "supplement_enrichment_status": "未补全",
        "ladder_tags": [],
        "ladder_tag_text": ""
      },
      {
        "actor_name": "木葉ちひろ",
        "code": "BANK-079",
        "title": "与美形素人美女的中出无剪辑拍摄！对超级纤细美女连续中出5发",
        "author": "",
        "release_date": "2022-05-13",
        "avfan_url": "https://avfan.com/zh-CN/movies/4Cmov7kL",
        "page_number": 1,
        "javtxt_enrichment_status": "无搜索结果",
        "javtxt_movie_id": "",
        "javtxt_url": "",
        "javtxt_tags": "",
        "javtxt_release_date": "",
        "author_raw": "",
        "video_category": "共演作品",
        "supplement_enrichment_status": "未补全",
        "ladder_tags": [],
        "ladder_tag_text": ""
      },
      {
        "actor_name": "木葉ちひろ",
        "code": "BANK-053",
        "title": "这么嚣张啊!? 超可爱的无毛纤细美人辣妹",
        "author": "碧棺りか",
        "release_date": "2021-09-10",
        "avfan_url": "https://avfan.com/zh-CN/movies/pP1V6JwN",
        "page_number": 1,
        "javtxt_enrichment_status": "已补全",
        "javtxt_movie_id": "383827",
        "javtxt_url": "https://javtxt.top/v/383827",
        "javtxt_tags": "中出 颜射 辣妹 苗条 白虎 美乳 制服 单体作品 高清",
        "javtxt_release_date": "2021-09-10",
        "author_raw": "碧棺りか",
        "video_category": "单体作品",
        "supplement_enrichment_status": "未补全",
        "ladder_tags": [],
        "ladder_tag_text": ""
      },
      {
        "actor_name": "木葉ちひろ",
        "code": "BTGL-018",
        "title": "りん",
        "author": "",
        "release_date": "2021-09-09",
        "avfan_url": "https://avfan.com/zh-CN/movies/dW55AkDF",
        "page_number": 1,
        "javtxt_enrichment_status": "已补全",
        "javtxt_movie_id": "384262",
        "javtxt_url": "https://javtxt.top/v/384262",
        "javtxt_tags": "颜射 白虎 中出 苗条 素人 配信専用",
        "javtxt_release_date": "2021-09-09",
        "author_raw": "未公开",
        "video_category": "",
        "supplement_enrichment_status": "未补全",
        "ladder_tags": [],
        "ladder_tag_text": ""
      },
      {
        "actor_name": "木葉ちひろ",
        "code": "BANS-005",
        "title": "ニイハオサイコウ",
        "author": "",
        "release_date": "2021-09-04",
        "avfan_url": "https://avfan.com/zh-CN/movies/fOyxwPiU",
        "page_number": 1,
        "javtxt_enrichment_status": "已补全",
        "javtxt_movie_id": "383362",
        "javtxt_url": "https://javtxt.top/v/383362",
        "javtxt_tags": "巨臀 搭讪 中出 辣妹 角色扮演 妄想族 独家分发 高清",
        "javtxt_release_date": "2021-09-04",
        "author_raw": "未公开",
        "video_category": "",
        "supplement_enrichment_status": "未补全",
        "ladder_tags": [],
        "ladder_tag_text": ""
      },
      {
        "actor_name": "木葉ちひろ",
        "code": "BANK-049",
        "title": "与美形素人女子无剪辑中出拍摄！敏感度超群的无毛纤细美人OL",
        "author": "",
        "release_date": "2021-08-13",
        "avfan_url": "https://avfan.com/zh-CN/movies/SJp9RQVO",
        "page_number": 1,
        "javtxt_enrichment_status": "已补全",
        "javtxt_movie_id": "381646",
        "javtxt_url": "https://javtxt.top/v/381646",
        "javtxt_tags": "中出 颜射 苗条 白虎 美乳 制服 泡泡袜 高清",
        "javtxt_release_date": "2021-08-13",
        "author_raw": "未公开",
        "video_category": "共演作品",
        "supplement_enrichment_status": "未补全",
        "ladder_tags": [],
        "ladder_tag_text": ""
      },
      {
        "actor_name": "木葉ちひろ",
        "code": "BTGL-014",
        "title": "梨々花",
        "author": "",
        "release_date": "2021-08-12",
        "avfan_url": "https://avfan.com/zh-CN/movies/NB071WgU",
        "page_number": 1,
        "javtxt_enrichment_status": "已补全",
        "javtxt_movie_id": "382013",
        "javtxt_url": "https://javtxt.top/v/382013",
        "javtxt_tags": "配信専用 素人 苗条 中出 白虎 美乳",
        "javtxt_release_date": "2021-08-12",
        "author_raw": "未公开",
        "video_category": "",
        "supplement_enrichment_status": "未补全",
        "ladder_tags": [],
        "ladder_tag_text": ""
      },
      {
        "actor_name": "木葉ちひろ",
        "code": "ELLO-015",
        "title": "りかchan",
        "author": "",
        "release_date": "2021-08-01",
        "avfan_url": "https://avfan.com/zh-CN/movies/5mC8N4MP",
        "page_number": 1,
        "javtxt_enrichment_status": "已补全",
        "javtxt_movie_id": "381331",
        "javtxt_url": "https://javtxt.top/v/381331",
        "javtxt_tags": "配信専用 素人 辣妹 搭讪 偶像艺人 苗条",
        "javtxt_release_date": "2021-08-01",
        "author_raw": "未公开",
        "video_category": "",
        "supplement_enrichment_status": "未补全",
        "ladder_tags": [],
        "ladder_tag_text": ""
      },
      {
        "actor_name": "木葉ちひろ",
        "code": "JUL-613",
        "title": "華奢なのに、激しいのがお好き―。 超極細、超小顔、腰砕けワイフ。 碧棺りか 28 歳 AV",
        "author": "碧棺りか",
        "release_date": "2021-06-19",
        "avfan_url": "https://avfan.com/zh-CN/movies/41ahLv7k",
        "page_number": 1,
        "javtxt_enrichment_status": "已补全",
        "javtxt_movie_id": "344143",
        "javtxt_url": "https://javtxt.top/v/344143",
        "javtxt_tags": "高清 独家分发 熟女 处女作 人妻・主妇 苗条 美乳 单体作品 数位马赛克",
        "javtxt_release_date": "2021-06-19",
        "author_raw": "碧棺りか",
        "video_category": "单体作品",
        "supplement_enrichment_status": "未补全",
        "ladder_tags": [],
        "ladder_tag_text": ""
      },
      {
        "actor_name": "木葉ちひろ",
        "code": "HEYZO-2468",
        "title": "性感按摩带来极致快感！-",
        "author": "",
        "release_date": "2021-02-25",
        "avfan_url": "https://avfan.com/zh-CN/movies/LZKhOzhq",
        "page_number": 1,
        "javtxt_enrichment_status": "无搜索结果",
        "javtxt_movie_id": "",
        "javtxt_url": "",
        "javtxt_tags": "",
        "javtxt_release_date": "",
        "author_raw": "",
        "video_category": "",
        "supplement_enrichment_status": "未补全",
        "ladder_tags": [],
        "ladder_tag_text": ""
      },
      {
        "actor_name": "木葉ちひろ",
        "code": "N-1496",
        "title": "n1496",
        "author": "",
        "release_date": "2020-09-22",
        "avfan_url": "https://avfan.com/zh-CN/movies/HeboU7nr",
        "page_number": 1,
        "javtxt_enrichment_status": "无搜索结果",
        "javtxt_movie_id": "",
        "javtxt_url": "",
        "javtxt_tags": "",
        "javtxt_release_date": "",
        "author_raw": "",
        "video_category": "",
        "supplement_enrichment_status": "未补全",
        "ladder_tags": [],
        "ladder_tag_text": ""
      },
      {
        "actor_name": "木葉ちひろ",
        "code": "N-1453",
        "title": "n1453",
        "author": "",
        "release_date": "2020-03-31",
        "avfan_url": "https://avfan.com/zh-CN/movies/r5Af2Lv1",
        "page_number": 1,
        "javtxt_enrichment_status": "无搜索结果",
        "javtxt_movie_id": "",
        "javtxt_url": "",
        "javtxt_tags": "",
        "javtxt_release_date": "",
        "author_raw": "",
        "video_category": "",
        "supplement_enrichment_status": "未补全",
        "ladder_tags": [],
        "ladder_tag_text": ""
      },
      {
        "actor_name": "木葉ちひろ",
        "code": "N-1451",
        "title": "n1451",
        "author": "",
        "release_date": "2020-03-24",
        "avfan_url": "https://avfan.com/zh-CN/movies/L4zP2Ozh",
        "page_number": 1,
        "javtxt_enrichment_status": "无搜索结果",
        "javtxt_movie_id": "",
        "javtxt_url": "",
        "javtxt_tags": "",
        "javtxt_release_date": "",
        "author_raw": "",
        "video_category": "",
        "supplement_enrichment_status": "未补全",
        "ladder_tags": [],
        "ladder_tag_text": ""
      },
      {
        "actor_name": "木葉ちひろ",
        "code": "N-1450",
        "title": "n1450",
        "author": "",
        "release_date": "2020-03-17",
        "avfan_url": "https://avfan.com/zh-CN/movies/v1i5H0im",
        "page_number": 1,
        "javtxt_enrichment_status": "无搜索结果",
        "javtxt_movie_id": "",
        "javtxt_url": "",
        "javtxt_tags": "",
        "javtxt_release_date": "",
        "author_raw": "",
        "video_category": "",
        "supplement_enrichment_status": "未补全",
        "ladder_tags": [],
        "ladder_tag_text": ""
      },
      {
        "actor_name": "木葉ちひろ",
        "code": "N-1449",
        "title": "n1449",
        "author": "",
        "release_date": "2020-03-17",
        "avfan_url": "https://avfan.com/zh-CN/movies/xr6c4fWQ",
        "page_number": 1,
        "javtxt_enrichment_status": "无搜索结果",
        "javtxt_movie_id": "",
        "javtxt_url": "",
        "javtxt_tags": "",
        "javtxt_release_date": "",
        "author_raw": "",
        "video_category": "",
        "supplement_enrichment_status": "未补全",
        "ladder_tags": [],
        "ladder_tag_text": ""
      },
      {
        "actor_name": "木葉ちひろ",
        "code": "N-1448",
        "title": "n1448",
        "author": "",
        "release_date": "2020-03-10",
        "avfan_url": "https://avfan.com/zh-CN/movies/02u4Hm6i",
        "page_number": 1,
        "javtxt_enrichment_status": "无搜索结果",
        "javtxt_movie_id": "",
        "javtxt_url": "",
        "javtxt_tags": "",
        "javtxt_release_date": "",
        "author_raw": "",
        "video_category": "",
        "supplement_enrichment_status": "未补全",
        "ladder_tags": [],
        "ladder_tag_text": ""
      }
    ],
    "eligible_web_movies": [
      {
        "actor_name": "木葉ちひろ",
        "code": "PCR-134",
        "title": "知り合いの娘と二人っきりに…",
        "author": "",
        "release_date": "2024-05-24",
        "avfan_url": "https://avfan.com/zh-CN/movies/Om22K5H0",
        "page_number": 1,
        "javtxt_enrichment_status": "无搜索结果",
        "javtxt_movie_id": "",
        "javtxt_url": "",
        "javtxt_tags": "",
        "javtxt_release_date": "",
        "author_raw": "",
        "video_category": "",
        "supplement_enrichment_status": "未补全",
        "ladder_tags": [],
        "ladder_tag_text": ""
      },
      {
        "actor_name": "木葉ちひろ",
        "code": "BSKC-032",
        "title": "歯科衛生士/社会人",
        "author": "",
        "release_date": "2023-09-29",
        "avfan_url": "https://avfan.com/zh-CN/movies/ZtGc6JcL",
        "page_number": 1,
        "javtxt_enrichment_status": "无搜索结果",
        "javtxt_movie_id": "",
        "javtxt_url": "",
        "javtxt_tags": "",
        "javtxt_release_date": "",
        "author_raw": "",
        "video_category": "",
        "supplement_enrichment_status": "未补全",
        "ladder_tags": [],
        "ladder_tag_text": ""
      },
      {
        "actor_name": "木葉ちひろ",
        "code": "ERHV-008",
        "title": "西○布高級ラウンジ嬢R 太パパとのプライベートハメ撮り映像流出",
        "author": "",
        "release_date": "2023-06-27",
        "avfan_url": "https://avfan.com/zh-CN/movies/v2wtn0im",
        "page_number": 1,
        "javtxt_enrichment_status": "已补全",
        "javtxt_movie_id": "441827",
        "javtxt_url": "https://javtxt.top/v/441827",
        "javtxt_tags": "高清 口交 中出 第一人称 苗条",
        "javtxt_release_date": "2023-06-27",
        "author_raw": "未公开",
        "video_category": "",
        "supplement_enrichment_status": "未补全",
        "ladder_tags": [],
        "ladder_tag_text": ""
      },
      {
        "actor_name": "木葉ちひろ",
        "code": "HNHU-053",
        "title": "個撮ナンパ ＃天使級美女 ＃アニ声オナニー ＃ なま中出し ＃ ねっとり系ジュボフェラ ＃",
        "author": "",
        "release_date": "2023-04-02",
        "avfan_url": "https://avfan.com/zh-CN/movies/dWK9pkDF",
        "page_number": 1,
        "javtxt_enrichment_status": "已补全",
        "javtxt_movie_id": "434250",
        "javtxt_url": "https://javtxt.top/v/434250",
        "javtxt_tags": "素人 搭讪 手淫 中出 美乳 口交 高清",
        "javtxt_release_date": "2023-04-02",
        "author_raw": "未公开",
        "video_category": "",
        "supplement_enrichment_status": "未补全",
        "ladder_tags": [],
        "ladder_tag_text": ""
      },
      {
        "actor_name": "木葉ちひろ",
        "code": "BANK-079",
        "title": "与美形素人美女的中出无剪辑拍摄！对超级纤细美女连续中出5发",
        "author": "",
        "release_date": "2022-05-13",
        "avfan_url": "https://avfan.com/zh-CN/movies/4Cmov7kL",
        "page_number": 1,
        "javtxt_enrichment_status": "无搜索结果",
        "javtxt_movie_id": "",
        "javtxt_url": "",
        "javtxt_tags": "",
        "javtxt_release_date": "",
        "author_raw": "",
        "video_category": "共演作品",
        "supplement_enrichment_status": "未补全",
        "ladder_tags": [],
        "ladder_tag_text": ""
      },
      {
        "actor_name": "木葉ちひろ",
        "code": "BANK-053",
        "title": "这么嚣张啊!? 超可爱的无毛纤细美人辣妹",
        "author": "碧棺りか",
        "release_date": "2021-09-10",
        "avfan_url": "https://avfan.com/zh-CN/movies/pP1V6JwN",
        "page_number": 1,
        "javtxt_enrichment_status": "已补全",
        "javtxt_movie_id": "383827",
        "javtxt_url": "https://javtxt.top/v/383827",
        "javtxt_tags": "中出 颜射 辣妹 苗条 白虎 美乳 制服 单体作品 高清",
        "javtxt_release_date": "2021-09-10",
        "author_raw": "碧棺りか",
        "video_category": "单体作品",
        "supplement_enrichment_status": "未补全",
        "ladder_tags": [],
        "ladder_tag_text": ""
      },
      {
        "actor_name": "木葉ちひろ",
        "code": "BTGL-018",
        "title": "りん",
        "author": "",
        "release_date": "2021-09-09",
        "avfan_url": "https://avfan.com/zh-CN/movies/dW55AkDF",
        "page_number": 1,
        "javtxt_enrichment_status": "已补全",
        "javtxt_movie_id": "384262",
        "javtxt_url": "https://javtxt.top/v/384262",
        "javtxt_tags": "颜射 白虎 中出 苗条 素人 配信専用",
        "javtxt_release_date": "2021-09-09",
        "author_raw": "未公开",
        "video_category": "",
        "supplement_enrichment_status": "未补全",
        "ladder_tags": [],
        "ladder_tag_text": ""
      },
      {
        "actor_name": "木葉ちひろ",
        "code": "BANS-005",
        "title": "ニイハオサイコウ",
        "author": "",
        "release_date": "2021-09-04",
        "avfan_url": "https://avfan.com/zh-CN/movies/fOyxwPiU",
        "page_number": 1,
        "javtxt_enrichment_status": "已补全",
        "javtxt_movie_id": "383362",
        "javtxt_url": "https://javtxt.top/v/383362",
        "javtxt_tags": "巨臀 搭讪 中出 辣妹 角色扮演 妄想族 独家分发 高清",
        "javtxt_release_date": "2021-09-04",
        "author_raw": "未公开",
        "video_category": "",
        "supplement_enrichment_status": "未补全",
        "ladder_tags": [],
        "ladder_tag_text": ""
      },
      {
        "actor_name": "木葉ちひろ",
        "code": "BANK-049",
        "title": "与美形素人女子无剪辑中出拍摄！敏感度超群的无毛纤细美人OL",
        "author": "",
        "release_date": "2021-08-13",
        "avfan_url": "https://avfan.com/zh-CN/movies/SJp9RQVO",
        "page_number": 1,
        "javtxt_enrichment_status": "已补全",
        "javtxt_movie_id": "381646",
        "javtxt_url": "https://javtxt.top/v/381646",
        "javtxt_tags": "中出 颜射 苗条 白虎 美乳 制服 泡泡袜 高清",
        "javtxt_release_date": "2021-08-13",
        "author_raw": "未公开",
        "video_category": "共演作品",
        "supplement_enrichment_status": "未补全",
        "ladder_tags": [],
        "ladder_tag_text": ""
      },
      {
        "actor_name": "木葉ちひろ",
        "code": "BTGL-014",
        "title": "梨々花",
        "author": "",
        "release_date": "2021-08-12",
        "avfan_url": "https://avfan.com/zh-CN/movies/NB071WgU",
        "page_number": 1,
        "javtxt_enrichment_status": "已补全",
        "javtxt_movie_id": "382013",
        "javtxt_url": "https://javtxt.top/v/382013",
        "javtxt_tags": "配信専用 素人 苗条 中出 白虎 美乳",
        "javtxt_release_date": "2021-08-12",
        "author_raw": "未公开",
        "video_category": "",
        "supplement_enrichment_status": "未补全",
        "ladder_tags": [],
        "ladder_tag_text": ""
      },
      {
        "actor_name": "木葉ちひろ",
        "code": "ELLO-015",
        "title": "りかchan",
        "author": "",
        "release_date": "2021-08-01",
        "avfan_url": "https://avfan.com/zh-CN/movies/5mC8N4MP",
        "page_number": 1,
        "javtxt_enrichment_status": "已补全",
        "javtxt_movie_id": "381331",
        "javtxt_url": "https://javtxt.top/v/381331",
        "javtxt_tags": "配信専用 素人 辣妹 搭讪 偶像艺人 苗条",
        "javtxt_release_date": "2021-08-01",
        "author_raw": "未公开",
        "video_category": "",
        "supplement_enrichment_status": "未补全",
        "ladder_tags": [],
        "ladder_tag_text": ""
      },
      {
        "actor_name": "木葉ちひろ",
        "code": "JUL-613",
        "title": "華奢なのに、激しいのがお好き―。 超極細、超小顔、腰砕けワイフ。 碧棺りか 28 歳 AV",
        "author": "碧棺りか",
        "release_date": "2021-06-19",
        "avfan_url": "https://avfan.com/zh-CN/movies/41ahLv7k",
        "page_number": 1,
        "javtxt_enrichment_status": "已补全",
        "javtxt_movie_id": "344143",
        "javtxt_url": "https://javtxt.top/v/344143",
        "javtxt_tags": "高清 独家分发 熟女 处女作 人妻・主妇 苗条 美乳 单体作品 数位马赛克",
        "javtxt_release_date": "2021-06-19",
        "author_raw": "碧棺りか",
        "video_category": "单体作品",
        "supplement_enrichment_status": "未补全",
        "ladder_tags": [],
        "ladder_tag_text": ""
      },
      {
        "actor_name": "木葉ちひろ",
        "code": "HEYZO-2468",
        "title": "性感按摩带来极致快感！-",
        "author": "",
        "release_date": "2021-02-25",
        "avfan_url": "https://avfan.com/zh-CN/movies/LZKhOzhq",
        "page_number": 1,
        "javtxt_enrichment_status": "无搜索结果",
        "javtxt_movie_id": "",
        "javtxt_url": "",
        "javtxt_tags": "",
        "javtxt_release_date": "",
        "author_raw": "",
        "video_category": "",
        "supplement_enrichment_status": "未补全",
        "ladder_tags": [],
        "ladder_tag_text": ""
      },
      {
        "actor_name": "木葉ちひろ",
        "code": "N-1496",
        "title": "n1496",
        "author": "",
        "release_date": "2020-09-22",
        "avfan_url": "https://avfan.com/zh-CN/movies/HeboU7nr",
        "page_number": 1,
        "javtxt_enrichment_status": "无搜索结果",
        "javtxt_movie_id": "",
        "javtxt_url": "",
        "javtxt_tags": "",
        "javtxt_release_date": "",
        "author_raw": "",
        "video_category": "",
        "supplement_enrichment_status": "未补全",
        "ladder_tags": [],
        "ladder_tag_text": ""
      },
      {
        "actor_name": "木葉ちひろ",
        "code": "N-1453",
        "title": "n1453",
        "author": "",
        "release_date": "2020-03-31",
        "avfan_url": "https://avfan.com/zh-CN/movies/r5Af2Lv1",
        "page_number": 1,
        "javtxt_enrichment_status": "无搜索结果",
        "javtxt_movie_id": "",
        "javtxt_url": "",
        "javtxt_tags": "",
        "javtxt_release_date": "",
        "author_raw": "",
        "video_category": "",
        "supplement_enrichment_status": "未补全",
        "ladder_tags": [],
        "ladder_tag_text": ""
      },
      {
        "actor_name": "木葉ちひろ",
        "code": "N-1451",
        "title": "n1451",
        "author": "",
        "release_date": "2020-03-24",
        "avfan_url": "https://avfan.com/zh-CN/movies/L4zP2Ozh",
        "page_number": 1,
        "javtxt_enrichment_status": "无搜索结果",
        "javtxt_movie_id": "",
        "javtxt_url": "",
        "javtxt_tags": "",
        "javtxt_release_date": "",
        "author_raw": "",
        "video_category": "",
        "supplement_enrichment_status": "未补全",
        "ladder_tags": [],
        "ladder_tag_text": ""
      },
      {
        "actor_name": "木葉ちひろ",
        "code": "N-1450",
        "title": "n1450",
        "author": "",
        "release_date": "2020-03-17",
        "avfan_url": "https://avfan.com/zh-CN/movies/v1i5H0im",
        "page_number": 1,
        "javtxt_enrichment_status": "无搜索结果",
        "javtxt_movie_id": "",
        "javtxt_url": "",
        "javtxt_tags": "",
        "javtxt_release_date": "",
        "author_raw": "",
        "video_category": "",
        "supplement_enrichment_status": "未补全",
        "ladder_tags": [],
        "ladder_tag_text": ""
      },
      {
        "actor_name": "木葉ちひろ",
        "code": "N-1449",
        "title": "n1449",
        "author": "",
        "release_date": "2020-03-17",
        "avfan_url": "https://avfan.com/zh-CN/movies/xr6c4fWQ",
        "page_number": 1,
        "javtxt_enrichment_status": "无搜索结果",
        "javtxt_movie_id": "",
        "javtxt_url": "",
        "javtxt_tags": "",
        "javtxt_release_date": "",
        "author_raw": "",
        "video_category": "",
        "supplement_enrichment_status": "未补全",
        "ladder_tags": [],
        "ladder_tag_text": ""
      },
      {
        "actor_name": "木葉ちひろ",
        "code": "N-1448",
        "title": "n1448",
        "author": "",
        "release_date": "2020-03-10",
        "avfan_url": "https://avfan.com/zh-CN/movies/02u4Hm6i",
        "page_number": 1,
        "javtxt_enrichment_status": "无搜索结果",
        "javtxt_movie_id": "",
        "javtxt_url": "",
        "javtxt_tags": "",
        "javtxt_release_date": "",
        "author_raw": "",
        "video_category": "",
        "supplement_enrichment_status": "未补全",
        "ladder_tags": [],
        "ladder_tag_text": ""
      }
    ],
    "collaborator_sections": [],
    "raw_web_movie_count": 64
  },
  "refreshed_at": "2026-07-08 09:14:28",
  "refresh_duration_ms": 220,
  "refresh_duration_text": "0秒"
}